Workbook
Name PARAM_PCT_KAS: PARAMETER!$B$13
Name PARAM_MARGIN_TARGET: PARAMETER!$B$7
Name PARAM_PCT_HASAN: PARAMETER!$B$12
Name PARAM_REJECT_MAX: PARAMETER!$B$5
Name PARAM_HPP_TIPIS: PARAMETER!$B$10
Name PARAM_PCT_JEEHANA: PARAMETER!$B$11
Name PARAM_OVERHEAD_PCT: PARAMETER!$B$9
Name PARAM_REJECT_MAJOR: PARAMETER!$B$6
Name PARAM_MARGIN_WARNING: PARAMETER!$B$8

Sheet PANDUAN
A1: ◆ HUZN AI BUSINESS OPERATING SYSTEM · v10 ULTRA EDITION ◆
A2: Dibangun untuk jangka panjang · Kapasitas: 50 produk · 50 material · 200 order · 1.000 transaksi
A4: ◈ ARSITEKTUR SISTEM — Aliran Data & Peran Setiap Sheet
A5: SHEET | B5: PERAN | C5: INPUT MANUAL | D5: KAPASITAS | E5: REFERENSI KE | F5: WARNA TAB | G5: PRIORITAS
A6: PANDUAN | B6: Dokumen panduan & referensi sistem ini | C6: Tidak ada | D6: — | E6: — | F6: Emas | G6: —
A7: PRODUK | B7: Master database semua produk — SATU-SATUNYA sumber produk | C7: PRODUCT_ID, Nama, HPP, Harga | D7: 50 produk | E7: Direferensi seluruh engine | F7: Hijau | G7: 1
A8: MATERIAL | B8: Database bahan baku & supplier | C8: MATERIAL_ID, Nama, Harga | D8: 50 material | E8: Referensi manual saat hitung bahan | F8: Biru tua | G8: 2
A9: PARAMETER | B9: Konfigurasi global 9 Named Range — pengatur seluruh sistem | C9: Nilai % kolom B SAJA | D9: 9 param | E9: HPP_ENGINE, PRODUCTION_PLAN, AI_ANALYSIS | F9: Merah | G9: 3
A10: HPP_ENGINE | B10: Hitung Harga Pokok Produksi per order → HPP/pcs otomatis | C10: ORDER_ID, QTY, Biaya aktual | D10: 200 order | E10: PRODUK (nama, target HPP) | F10: Biru | G10: 4
A11: PRODUCTION_PLAN | B11: Tracking produksi, jadwal, QC, aging per order | C11: ORDER_ID, Klien, QTY, Tanggal | D11: 200 order | E11: PARAMETER (reject max) | F11: Ungu | G11: 5
A12: SALES_TRACKER | B12: Setiap transaksi penjualan — Revenue & Profit real-time | C12: Tanggal, ORDER_ID, QTY jual | D12: 1.000 trx | E12: PRODUK (harga jual), HPP_ENGINE (HPP/pcs) | F12: Teal | G12: 6
A13: SUMMARY_ENGINE | B13: Rekap keuangan lengkap per order — NO INPUT sama sekali | C13: ORDER_ID di kolom A saja | D13: 200 order | E13: PRODUK, HPP_ENGINE, PRODUCTION_PLAN, SALES_TRACKER | F13: Abu | G13: 7
A14: CASHFLOW | B14: Setiap arus kas masuk & keluar — saldo kumulatif otomatis | C14: Tanggal, Tipe, Nominal, Kat. | D14: 1.000 trx | E14: — (independen) | F14: Ungu tua | G14: 8
A15: AI_ANALYSIS | B15: KPI insight + distribusi profit otomatis untuk laporan | C15: Tidak ada | D15: — | E15: SUMMARY_ENGINE, CASHFLOW, PRODUCTION_PLAN | F15: Oranye | G15: 9
A16: DASHBOARD | B16: Ringkasan eksekutif real-time — tampilan manajemen | C16: Tidak ada | D16: — | E16: SUMMARY_ENGINE, CASHFLOW, PRODUCTION_PLAN | F16: Emas | G16: 10
A18: ◈ CARA KERJA HARIAN — Urutan Input yang Benar
A19: LANGKAH | B19: AKSI | C19: DETAIL LENGKAP | D19: SHEET TUJUAN | E19: KOLOM INPUT | F19: EFEK KE SISTEM | G19: WAKTU EST.
A20: 1 | B20: ORDER BARU MASUK | C20: Isi ORDER_ID baru, PRODUCT_ID, Klien, QTY Plan, Tanggal Mulai & Selesai, Status = Planning | D20: PRODUCTION_PLAN | E20: A,B,C,D,F,G,H | F20: Status & aging terhitung otomatis. Dashboard order count naik. | G20: 2 menit
A21: 2 | B21: MULAI PRODUKSI | C21: Isi ORDER_ID, PRODUCT_ID, QTY Produksi, Biaya Bahan, TK, QC aktual | D21: HPP_ENGINE | E21: A,B,D,E,F,G | F21: Overhead dihitung otomatis. HPP/pcs & status HPP muncul. Summary Engine update. | G21: 3 menit
A22: 3 | B22: UPDATE STATUS | C22: Ubah STATUS ORDER: Planning → Produksi → Sample → Selesai | D22: PRODUCTION_PLAN | E22: Kolom H | F22: Dashboard status count update. Summary Engine status order berubah. | G22: 30 detik
A23: 4 | B23: ADA PENJUALAN | C23: Isi Tanggal, ORDER_ID, PRODUCT_ID, QTY Terjual per transaksi | D23: SALES_TRACKER | E23: A,B,C,E | F23: Revenue, HPP, Profit, Margin dihitung otomatis. Summary Engine revenue naik. | G23: 2 menit
A24: 5 | B24: CATAT CASHFLOW | C24: Isi setiap uang masuk (Revenue, DP, Pelunasan) atau keluar (Bahan, TK, Overhead) | D24: CASHFLOW | E24: A,B,C,D,E,F | F24: Saldo kumulatif update real-time. Status Kas ✓ AMAN / ⚡ KRITIS otomatis. | G24: 1 menit
A25: 6 | B25: LIHAT HASIL | C25: Buka DASHBOARD → semua KPI update otomatis. Cek AI_ANALYSIS untuk insight mendalam. | D25: DASHBOARD / AI_ANALYSIS | E25: — | F25: Visual KPI langsung terbaca. Insight & rekomendasi aksi tersedia. | G25: —
A26: 7 | B26: TAMBAH PRODUK | C26: Buka PRODUK → tambah baris baru di bawah data terakhir → isi PRODUCT_ID, nama, harga | D26: PRODUK | E26: A hingga H | F26: Produk baru langsung tersedia di dropdown HPP_ENGINE & SALES_TRACKER. | G26: 2 menit
A27: 8 | B27: UBAH PARAMETER | C27: Buka PARAMETER → ubah NILAI di kolom B SAJA → berlaku seketika ke seluruh sistem | D27: PARAMETER | E27: Kolom B saja | F27: Margin target, reject max, overhead %, distribusi profit — semua berubah serentak. | G27: 30 detik
A30: ◈ KODE WARNA FORMULA (Standar Industri Keuangan)
A31: ████ | B31: BIRU — Input Manual | D31: Angka/teks yang HARUS diisi pengguna. Jangan biarkan kosong jika baris sudah diisi.
A32: ████ | B32: EMAS — Formula Auto | D32: Dihitung otomatis sistem. JANGAN diubah. Warna berubah jika ada error.
A33: ████ | B33: HIJAU — Link Lintas Sheet | D33: Mengambil data dari sheet lain. Akan error jika ID sumber tidak ditemukan.
A34: ████ | B34: MERAH — Parameter Kritis | D34: Named Range / PARAMETER global. JANGAN ubah posisi baris/kolom.

Sheet DASHBOARD
A1: ◆ HUZN AI BUSINESS OPERATING SYSTEM · EXECUTIVE DASHBOARD ◆
A2: =IFERROR("Data per: "&TEXT(TODAY(),"DD MMMM YYYY")&" · Semua KPI update otomatis dari engine · Tidak ada input manual di sheet ini","—") -> Data per: 13 April 2026 · Semua KPI update otomatis dari engine · Tidak ada input manual di sheet ini
A3: ◈ KEUANGAN UTAMA
A4: TOTAL REVENUE | C4: TOTAL COST | E4: GROSS PROFIT | G4: MARGIN % AKTUAL | I4: SALDO KAS
A5: =IFERROR(SUMIFS(SUMMARY_ENGINE!$I:$I,SUMMARY_ENGINE!$A:$A,"HZN-*"),0) -> 113800000 | C5: =IFERROR(SUMIFS(SUMMARY_ENGINE!$H:$H,SUMMARY_ENGINE!$A:$A,"HZN-*"),0) -> 215967000 | E5: =IFERROR(SUMIFS(SUMMARY_ENGINE!$J:$J,SUMMARY_ENGINE!$A:$A,"HZN-*"),0) -> -102167000 | G5: =IFERROR(IF(A5=0,0,E5/A5),0) -> -0.8977768 | I5: {=IFERROR(INDEX(CASHFLOW!$G:$G,MATCH(2,1/(CASHFLOW!$A:$A<>""),1)),0)} -> 111300000
E6: =IF(E5>=0,"▲ Profit Positif","▼ Masih Rugi") -> ▼ Masih Rugi | G6: =IF(G5>=PARAM_MARGIN_TARGET,"▲ Di Atas Target","▼ Di Bawah Target") -> ▼ Di Bawah Target | I6: =IF(I5>=50000000,"▲ Kas Aman","▼ Monitor Kas") -> ▲ Kas Aman
A7: ◈ OPERASIONAL PRODUKSI & PENJUALAN
A8: TOTAL ORDER | C8: AKTIF PRODUKSI | E8: SELESAI | G8: TOTAL UNIT TERJUAL | I8: SELL-THRU RATE
A9: =IFERROR(COUNTA(SUMMARY_ENGINE!$A$4:$A$203),0) -> 7 | C9: =IFERROR(COUNTIFS(PRODUCTION_PLAN!$H$4:$H$203,"Produksi")+COUNTIFS(PRODUCTION_PLAN!$H$4:$H$203,"Sample"),0) -> 5 | E9: =IFERROR(COUNTIFS(PRODUCTION_PLAN!$H$4:$H$203,"Selesai"),0) -> 1 | G9: =IFERROR(SUMIFS(SUMMARY_ENGINE!$F$4:$F$203,SUMMARY_ENGINE!$A$4:$A$203,"HZN-*"),0) -> 368 | I9: =IFERROR(IF(SUMIFS(SUMMARY_ENGINE!$E$4:$E$203,SUMMARY_ENGINE!$A$4:$A$203,"HZN-*")=0,0,SUMIFS(SUMMARY_ENGINE!$F$4:$F$203,SUMMARY_ENGINE!$A$4:$A$203,"HZN-*")/SUMIFS(SUMMARY_ENGINE!$E$4:$E$203,SUMMARY_ENGINE!$A$4:$A$203,"HZN-*")),0) -> 0.37059416
A10: ◈ REKAP PER ORDER — Live dari SUMMARY ENGINE
A11: ORDER_ID | B11: PRODUK | C11: QTY PROD | D11: QTY JUAL | E11: REVENUE (Rp) | F11: COST (Rp) | G11: PROFIT (Rp) | H11: MARGIN % | I11: SELL THRU % | J11: STATUS
A12: =IFERROR(IF(SUMMARY_ENGINE!A4="","",SUMMARY_ENGINE!A4),"") -> HZN-2604-001 | B12: =IFERROR(IF(SUMMARY_ENGINE!A4="","",SUMMARY_ENGINE!C4),"") -> Abaya Premium Linen | C12: =IFERROR(SUMMARY_ENGINE!E4,0) -> 148 | D12: =IFERROR(SUMMARY_ENGINE!F4,0) -> 148 | E12: =IFERROR(SUMMARY_ENGINE!I4,0) -> 51800000 | F12: =IFERROR(SUMMARY_ENGINE!H4,0) -> 28753000 | G12: =IFERROR(SUMMARY_ENGINE!J4,0) -> 23047000 | H12: =IFERROR(SUMMARY_ENGINE!K4,0) -> 0.44492278 | I12: =IFERROR(SUMMARY_ENGINE!M4,0) -> 1 | J12: =IFERROR(SUMMARY_ENGINE!N4,"—") -> SOLD OUT
A13: =IFERROR(IF(SUMMARY_ENGINE!A5="","",SUMMARY_ENGINE!A5),"") -> HZN-2604-002 | B13: =IFERROR(IF(SUMMARY_ENGINE!A5="","",SUMMARY_ENGINE!C5),"") -> Gamis Velvet Bordir | C13: =IFERROR(SUMMARY_ENGINE!E5,0) -> 185 | D13: =IFERROR(SUMMARY_ENGINE!F5,0) -> 0 | E13: =IFERROR(SUMMARY_ENGINE!I5,0) -> 0 | F13: =IFERROR(SUMMARY_ENGINE!H5,0) -> 45628000 | G13: =IFERROR(SUMMARY_ENGINE!J5,0) -> -45628000 | H13: =IFERROR(SUMMARY_ENGINE!K5,0) -> -1 | I13: =IFERROR(SUMMARY_ENGINE!M5,0) -> 0 | J13: =IFERROR(SUMMARY_ENGINE!N5,"—") -> BELUM TERJUAL
A14: =IFERROR(IF(SUMMARY_ENGINE!A6="","",SUMMARY_ENGINE!A6),"") -> HZN-2604-003 | B14: =IFERROR(IF(SUMMARY_ENGINE!A6="","",SUMMARY_ENGINE!C6),"") -> Kaftan Silk Premium | C14: =IFERROR(SUMMARY_ENGINE!E6,0) -> 80 | D14: =IFERROR(SUMMARY_ENGINE!F6,0) -> 0 | E14: =IFERROR(SUMMARY_ENGINE!I6,0) -> 0 | F14: =IFERROR(SUMMARY_ENGINE!H6,0) -> 22152000 | G14: =IFERROR(SUMMARY_ENGINE!J6,0) -> -22152000 | H14: =IFERROR(SUMMARY_ENGINE!K6,0) -> -1 | I14: =IFERROR(SUMMARY_ENGINE!M6,0) -> 0 | J14: =IFERROR(SUMMARY_ENGINE!N6,"—") -> BELUM TERJUAL
A15: =IFERROR(IF(SUMMARY_ENGINE!A7="","",SUMMARY_ENGINE!A7),"") -> HZN-2604-004 | B15: =IFERROR(IF(SUMMARY_ENGINE!A7="","",SUMMARY_ENGINE!C7),"") -> Tunik Casual Linen | C15: =IFERROR(SUMMARY_ENGINE!E7,0) -> 120 | D15: =IFERROR(SUMMARY_ENGINE!F7,0) -> 120 | E15: =IFERROR(SUMMARY_ENGINE!I7,0) -> 27000000 | F15: =IFERROR(SUMMARY_ENGINE!H7,0) -> 14898000 | G15: =IFERROR(SUMMARY_ENGINE!J7,0) -> 12102000 | H15: =IFERROR(SUMMARY_ENGINE!K7,0) -> 0.44822222 | I15: =IFERROR(SUMMARY_ENGINE!M7,0) -> 1 | J15: =IFERROR(SUMMARY_ENGINE!N7,"—") -> SOLD OUT
A16: =IFERROR(IF(SUMMARY_ENGINE!A8="","",SUMMARY_ENGINE!A8),"") -> HZN-2604-005 | B16: =IFERROR(IF(SUMMARY_ENGINE!A8="","",SUMMARY_ENGINE!C8),"") -> Dress Batik Modern | C16: =IFERROR(SUMMARY_ENGINE!E8,0) -> 50 | D16: =IFERROR(SUMMARY_ENGINE!F8,0) -> 0 | E16: =IFERROR(SUMMARY_ENGINE!I8,0) -> 0 | F16: =IFERROR(SUMMARY_ENGINE!H8,0) -> 15800000 | G16: =IFERROR(SUMMARY_ENGINE!J8,0) -> -15800000 | H16: =IFERROR(SUMMARY_ENGINE!K8,0) -> -1 | I16: =IFERROR(SUMMARY_ENGINE!M8,0) -> 0 | J16: =IFERROR(SUMMARY_ENGINE!N8,"—") -> BELUM TERJUAL
A17: =IFERROR(IF(SUMMARY_ENGINE!A9="","",SUMMARY_ENGINE!A9),"") -> HZN-2604-006 | B17: =IFERROR(IF(SUMMARY_ENGINE!A9="","",SUMMARY_ENGINE!C9),"") -> Abaya Premium Linen | C17: =IFERROR(SUMMARY_ENGINE!E9,0) -> 240 | D17: =IFERROR(SUMMARY_ENGINE!F9,0) -> 100 | E17: =IFERROR(SUMMARY_ENGINE!I9,0) -> 35000000 | F17: =IFERROR(SUMMARY_ENGINE!H9,0) -> 47715000 | G17: =IFERROR(SUMMARY_ENGINE!J9,0) -> -12715000 | H17: =IFERROR(SUMMARY_ENGINE!K9,0) -> -0.36328571 | I17: =IFERROR(SUMMARY_ENGINE!M9,0) -> 0.41666667 | J17: =IFERROR(SUMMARY_ENGINE!N9,"—") -> SLOW MOVE
A18: =IFERROR(IF(SUMMARY_ENGINE!A10="","",SUMMARY_ENGINE!A10),"") -> HZN-2604-007 | B18: =IFERROR(IF(SUMMARY_ENGINE!A10="","",SUMMARY_ENGINE!C10),"") -> Gamis Velvet Bordir | C18: =IFERROR(SUMMARY_ENGINE!E10,0) -> 170 | D18: =IFERROR(SUMMARY_ENGINE!F10,0) -> 0 | E18: =IFERROR(SUMMARY_ENGINE!I10,0) -> 0 | F18: =IFERROR(SUMMARY_ENGINE!H10,0) -> 41021000 | G18: =IFERROR(SUMMARY_ENGINE!J10,0) -> -41021000 | H18: =IFERROR(SUMMARY_ENGINE!K10,0) -> -1 | I18: =IFERROR(SUMMARY_ENGINE!M10,0) -> 0 | J18: =IFERROR(SUMMARY_ENGINE!N10,"—") -> BELUM TERJUAL
A19: =IFERROR(IF(SUMMARY_ENGINE!A11="","",SUMMARY_ENGINE!A11),"") | B19: =IFERROR(IF(SUMMARY_ENGINE!A11="","",SUMMARY_ENGINE!C11),"") | C19: =IFERROR(SUMMARY_ENGINE!E11,0) -> 0 | D19: =IFERROR(SUMMARY_ENGINE!F11,0) -> 0 | E19: =IFERROR(SUMMARY_ENGINE!I11,0) -> 0 | F19: =IFERROR(SUMMARY_ENGINE!H11,0) -> 0 | G19: =IFERROR(SUMMARY_ENGINE!J11,0) -> 0 | H19: =IFERROR(SUMMARY_ENGINE!K11,0) -> 0 | I19: =IFERROR(SUMMARY_ENGINE!M11,0) -> 0 | J19: =IFERROR(SUMMARY_ENGINE!N11,"—") -> —
A20: =IFERROR(IF(SUMMARY_ENGINE!A12="","",SUMMARY_ENGINE!A12),"") | B20: =IFERROR(IF(SUMMARY_ENGINE!A12="","",SUMMARY_ENGINE!C12),"") | C20: =IFERROR(SUMMARY_ENGINE!E12,0) -> 0 | D20: =IFERROR(SUMMARY_ENGINE!F12,0) -> 0 | E20: =IFERROR(SUMMARY_ENGINE!I12,0) -> 0 | F20: =IFERROR(SUMMARY_ENGINE!H12,0) -> 0 | G20: =IFERROR(SUMMARY_ENGINE!J12,0) -> 0 | H20: =IFERROR(SUMMARY_ENGINE!K12,0) -> 0 | I20: =IFERROR(SUMMARY_ENGINE!M12,0) -> 0 | J20: =IFERROR(SUMMARY_ENGINE!N12,"—") -> —
A21: =IFERROR(IF(SUMMARY_ENGINE!A13="","",SUMMARY_ENGINE!A13),"") | B21: =IFERROR(IF(SUMMARY_ENGINE!A13="","",SUMMARY_ENGINE!C13),"") | C21: =IFERROR(SUMMARY_ENGINE!E13,0) -> 0 | D21: =IFERROR(SUMMARY_ENGINE!F13,0) -> 0 | E21: =IFERROR(SUMMARY_ENGINE!I13,0) -> 0 | F21: =IFERROR(SUMMARY_ENGINE!H13,0) -> 0 | G21: =IFERROR(SUMMARY_ENGINE!J13,0) -> 0 | H21: =IFERROR(SUMMARY_ENGINE!K13,0) -> 0 | I21: =IFERROR(SUMMARY_ENGINE!M13,0) -> 0 | J21: =IFERROR(SUMMARY_ENGINE!N13,"—") -> —
A22: =IFERROR(IF(SUMMARY_ENGINE!A14="","",SUMMARY_ENGINE!A14),"") | B22: =IFERROR(IF(SUMMARY_ENGINE!A14="","",SUMMARY_ENGINE!C14),"") | C22: =IFERROR(SUMMARY_ENGINE!E14,0) -> 0 | D22: =IFERROR(SUMMARY_ENGINE!F14,0) -> 0 | E22: =IFERROR(SUMMARY_ENGINE!I14,0) -> 0 | F22: =IFERROR(SUMMARY_ENGINE!H14,0) -> 0 | G22: =IFERROR(SUMMARY_ENGINE!J14,0) -> 0 | H22: =IFERROR(SUMMARY_ENGINE!K14,0) -> 0 | I22: =IFERROR(SUMMARY_ENGINE!M14,0) -> 0 | J22: =IFERROR(SUMMARY_ENGINE!N14,"—") -> —
A23: =IFERROR(IF(SUMMARY_ENGINE!A15="","",SUMMARY_ENGINE!A15),"") | B23: =IFERROR(IF(SUMMARY_ENGINE!A15="","",SUMMARY_ENGINE!C15),"") | C23: =IFERROR(SUMMARY_ENGINE!E15,0) -> 0 | D23: =IFERROR(SUMMARY_ENGINE!F15,0) -> 0 | E23: =IFERROR(SUMMARY_ENGINE!I15,0) -> 0 | F23: =IFERROR(SUMMARY_ENGINE!H15,0) -> 0 | G23: =IFERROR(SUMMARY_ENGINE!J15,0) -> 0 | H23: =IFERROR(SUMMARY_ENGINE!K15,0) -> 0 | I23: =IFERROR(SUMMARY_ENGINE!M15,0) -> 0 | J23: =IFERROR(SUMMARY_ENGINE!N15,"—") -> —
... A51: =IFERROR(IF(SUMMARY_ENGINE!A43="","",SUMMARY_ENGINE!A43),"") | B51: =IFERROR(IF(SUMMARY_ENGINE!A43="","",SUMMARY_ENGINE!C43),"") | C51: =IFERROR(SUMMARY_ENGINE!E43,0) -> 0 | D51: =IFERROR(SUMMARY_ENGINE!F43,0) -> 0 | E51: =IFERROR(SUMMARY_ENGINE!I43,0) -> 0 | F51: =IFERROR(SUMMARY_ENGINE!H43,0) -> 0 | G51: =IFERROR(SUMMARY_ENGINE!J43,0) -> 0 | H51: =IFERROR(SUMMARY_ENGINE!K43,0) -> 0 | I51: =IFERROR(SUMMARY_ENGINE!M43,0) -> 0 | J51: =IFERROR(SUMMARY_ENGINE!N43,"—") -> —
A52: ◈ KPI LANJUTAN — Analisis Mendalam
A53: BURN RATE/BULAN | C53: =IFERROR(IF(COUNTA(CASHFLOW!$A$3:$A$1002)=0,0,ABS(SUMIFS(CASHFLOW!$D:$D,CASHFLOW!$C:$C,"Keluar"))/MAX(1,COUNTIFS(CASHFLOW!$I:$I,"<>")-1)),0) -> 137200 | E53: Rata-rata pengeluaran per bulan
A54: RUNWAY (Bulan) | C54: =IFERROR(IF(C53=0,"∞",MAX(CASHFLOW!$G:$G)/C53),0) -> 898.68805 | E54: Berapa bulan kas cukup dengan burn rate saat ini
A55: ORDER WIN RATE | C55: =IFERROR(IF(COUNTA(SUMMARY_ENGINE!$A$4:$A$203)=0,0,COUNTIFS(SUMMARY_ENGINE!$N:$N,"SOLD OUT")/COUNTA(SUMMARY_ENGINE!$A$4:$A$203)),0) -> 0.28571429 | E55: % order yang berhasil SOLD OUT
A56: AVG MARGIN / ORDER | C56: =IFERROR(AVERAGEIF(SUMMARY_ENGINE!$K$4:$K$203,">0",SUMMARY_ENGINE!$K$4:$K$203),0) -> 0.4465725 | E56: Rata-rata margin order yang sudah terjual
A57: STOK TERTAHAN (Rp) | C57: =IFERROR(SUMPRODUCT((SUMMARY_ENGINE!$G$4:$G$203>0)*(SUMMARY_ENGINE!$H$4:$H$203/SUMMARY_ENGINE!$E$4:$E$203)*SUMMARY_ENGINE!$G$4:$G$203),0) -> 0 | E57: Nilai HPP stok yang belum terjual
A58: =IFERROR(IF(SUMMARY_ENGINE!A50="","",SUMMARY_ENGINE!A50),"") | B58: =IFERROR(IF(SUMMARY_ENGINE!A50="","",SUMMARY_ENGINE!C50),"") | C58: =IFERROR(SUMMARY_ENGINE!E50,0) -> 0 | D58: =IFERROR(SUMMARY_ENGINE!F50,0) -> 0 | E58: =IFERROR(SUMMARY_ENGINE!I50,0) -> 0 | F58: =IFERROR(SUMMARY_ENGINE!H50,0) -> 0 | G58: =IFERROR(SUMMARY_ENGINE!J50,0) -> 0 | H58: =IFERROR(SUMMARY_ENGINE!K50,0) -> 0 | I58: =IFERROR(SUMMARY_ENGINE!M50,0) -> 0 | J58: =IFERROR(SUMMARY_ENGINE!N50,"—") -> —
A59: =IFERROR(IF(SUMMARY_ENGINE!A51="","",SUMMARY_ENGINE!A51),"") | B59: =IFERROR(IF(SUMMARY_ENGINE!A51="","",SUMMARY_ENGINE!C51),"") | C59: =IFERROR(SUMMARY_ENGINE!E51,0) -> 0 | D59: =IFERROR(SUMMARY_ENGINE!F51,0) -> 0 | E59: =IFERROR(SUMMARY_ENGINE!I51,0) -> 0 | F59: =IFERROR(SUMMARY_ENGINE!H51,0) -> 0 | G59: =IFERROR(SUMMARY_ENGINE!J51,0) -> 0 | H59: =IFERROR(SUMMARY_ENGINE!K51,0) -> 0 | I59: =IFERROR(SUMMARY_ENGINE!M51,0) -> 0 | J59: =IFERROR(SUMMARY_ENGINE!N51,"—") -> —
A60: =IFERROR(IF(SUMMARY_ENGINE!A52="","",SUMMARY_ENGINE!A52),"") | B60: =IFERROR(IF(SUMMARY_ENGINE!A52="","",SUMMARY_ENGINE!C52),"") | C60: =IFERROR(SUMMARY_ENGINE!E52,0) -> 0 | D60: =IFERROR(SUMMARY_ENGINE!F52,0) -> 0 | E60: =IFERROR(SUMMARY_ENGINE!I52,0) -> 0 | F60: =IFERROR(SUMMARY_ENGINE!H52,0) -> 0 | G60: =IFERROR(SUMMARY_ENGINE!J52,0) -> 0 | H60: =IFERROR(SUMMARY_ENGINE!K52,0) -> 0 | I60: =IFERROR(SUMMARY_ENGINE!M52,0) -> 0 | J60: =IFERROR(SUMMARY_ENGINE!N52,"—") -> —
A61: =IFERROR(IF(SUMMARY_ENGINE!A53="","",SUMMARY_ENGINE!A53),"") | B61: =IFERROR(IF(SUMMARY_ENGINE!A53="","",SUMMARY_ENGINE!C53),"") | C61: =IFERROR(SUMMARY_ENGINE!E53,0) -> 0 | D61: =IFERROR(SUMMARY_ENGINE!F53,0) -> 0 | E61: =IFERROR(SUMMARY_ENGINE!I53,0) -> 0 | F61: =IFERROR(SUMMARY_ENGINE!H53,0) -> 0 | G61: =IFERROR(SUMMARY_ENGINE!J53,0) -> 0 | H61: =IFERROR(SUMMARY_ENGINE!K53,0) -> 0 | I61: =IFERROR(SUMMARY_ENGINE!M53,0) -> 0 | J61: =IFERROR(SUMMARY_ENGINE!N53,"—") -> —
A62: =IFERROR(IF(SUMMARY_ENGINE!A54="","",SUMMARY_ENGINE!A54),"") | B62: =IFERROR(IF(SUMMARY_ENGINE!A54="","",SUMMARY_ENGINE!C54),"") | C62: =IFERROR(SUMMARY_ENGINE!E54,0) -> 0 | D62: =IFERROR(SUMMARY_ENGINE!F54,0) -> 0 | E62: =IFERROR(SUMMARY_ENGINE!I54,0) -> 0 | F62: =IFERROR(SUMMARY_ENGINE!H54,0) -> 0 | G62: =IFERROR(SUMMARY_ENGINE!J54,0) -> 0 | H62: =IFERROR(SUMMARY_ENGINE!K54,0) -> 0 | I62: =IFERROR(SUMMARY_ENGINE!M54,0) -> 0 | J62: =IFERROR(SUMMARY_ENGINE!N54,"—") -> —
A63: =IFERROR(IF(SUMMARY_ENGINE!A55="","",SUMMARY_ENGINE!A55),"") | B63: =IFERROR(IF(SUMMARY_ENGINE!A55="","",SUMMARY_ENGINE!C55),"") | C63: =IFERROR(SUMMARY_ENGINE!E55,0) -> 0 | D63: =IFERROR(SUMMARY_ENGINE!F55,0) -> 0 | E63: =IFERROR(SUMMARY_ENGINE!I55,0) -> 0 | F63: =IFERROR(SUMMARY_ENGINE!H55,0) -> 0 | G63: =IFERROR(SUMMARY_ENGINE!J55,0) -> 0 | H63: =IFERROR(SUMMARY_ENGINE!K55,0) -> 0 | I63: =IFERROR(SUMMARY_ENGINE!M55,0) -> 0 | J63: =IFERROR(SUMMARY_ENGINE!N55,"—") -> —
A64: =IFERROR(IF(SUMMARY_ENGINE!A56="","",SUMMARY_ENGINE!A56),"") | B64: =IFERROR(IF(SUMMARY_ENGINE!A56="","",SUMMARY_ENGINE!C56),"") | C64: =IFERROR(SUMMARY_ENGINE!E56,0) -> 0 | D64: =IFERROR(SUMMARY_ENGINE!F56,0) -> 0 | E64: =IFERROR(SUMMARY_ENGINE!I56,0) -> 0 | F64: =IFERROR(SUMMARY_ENGINE!H56,0) -> 0 | G64: =IFERROR(SUMMARY_ENGINE!J56,0) -> 0 | H64: =IFERROR(SUMMARY_ENGINE!K56,0) -> 0 | I64: =IFERROR(SUMMARY_ENGINE!M56,0) -> 0 | J64: =IFERROR(SUMMARY_ENGINE!N56,"—") -> —
A65: =IFERROR(IF(SUMMARY_ENGINE!A57="","",SUMMARY_ENGINE!A57),"") | B65: =IFERROR(IF(SUMMARY_ENGINE!A57="","",SUMMARY_ENGINE!C57),"") | C65: =IFERROR(SUMMARY_ENGINE!E57,0) -> 0 | D65: =IFERROR(SUMMARY_ENGINE!F57,0) -> 0 | E65: =IFERROR(SUMMARY_ENGINE!I57,0) -> 0 | F65: =IFERROR(SUMMARY_ENGINE!H57,0) -> 0 | G65: =IFERROR(SUMMARY_ENGINE!J57,0) -> 0 | H65: =IFERROR(SUMMARY_ENGINE!K57,0) -> 0 | I65: =IFERROR(SUMMARY_ENGINE!M57,0) -> 0 | J65: =IFERROR(SUMMARY_ENGINE!N57,"—") -> —
A66: =IFERROR(IF(SUMMARY_ENGINE!A58="","",SUMMARY_ENGINE!A58),"") | B66: =IFERROR(IF(SUMMARY_ENGINE!A58="","",SUMMARY_ENGINE!C58),"") | C66: =IFERROR(SUMMARY_ENGINE!E58,0) -> 0 | D66: =IFERROR(SUMMARY_ENGINE!F58,0) -> 0 | E66: =IFERROR(SUMMARY_ENGINE!I58,0) -> 0 | F66: =IFERROR(SUMMARY_ENGINE!H58,0) -> 0 | G66: =IFERROR(SUMMARY_ENGINE!J58,0) -> 0 | H66: =IFERROR(SUMMARY_ENGINE!K58,0) -> 0 | I66: =IFERROR(SUMMARY_ENGINE!M58,0) -> 0 | J66: =IFERROR(SUMMARY_ENGINE!N58,"—") -> —
A67: =IFERROR(IF(SUMMARY_ENGINE!A59="","",SUMMARY_ENGINE!A59),"") | B67: =IFERROR(IF(SUMMARY_ENGINE!A59="","",SUMMARY_ENGINE!C59),"") | C67: =IFERROR(SUMMARY_ENGINE!E59,0) -> 0 | D67: =IFERROR(SUMMARY_ENGINE!F59,0) -> 0 | E67: =IFERROR(SUMMARY_ENGINE!I59,0) -> 0 | F67: =IFERROR(SUMMARY_ENGINE!H59,0) -> 0 | G67: =IFERROR(SUMMARY_ENGINE!J59,0) -> 0 | H67: =IFERROR(SUMMARY_ENGINE!K59,0) -> 0 | I67: =IFERROR(SUMMARY_ENGINE!M59,0) -> 0 | J67: =IFERROR(SUMMARY_ENGINE!N59,"—") -> —
A68: =IFERROR(IF(SUMMARY_ENGINE!A60="","",SUMMARY_ENGINE!A60),"") | B68: =IFERROR(IF(SUMMARY_ENGINE!A60="","",SUMMARY_ENGINE!C60),"") | C68: =IFERROR(SUMMARY_ENGINE!E60,0) -> 0 | D68: =IFERROR(SUMMARY_ENGINE!F60,0) -> 0 | E68: =IFERROR(SUMMARY_ENGINE!I60,0) -> 0 | F68: =IFERROR(SUMMARY_ENGINE!H60,0) -> 0 | G68: =IFERROR(SUMMARY_ENGINE!J60,0) -> 0 | H68: =IFERROR(SUMMARY_ENGINE!K60,0) -> 0 | I68: =IFERROR(SUMMARY_ENGINE!M60,0) -> 0 | J68: =IFERROR(SUMMARY_ENGINE!N60,"—") -> —
A69: =IFERROR(IF(SUMMARY_ENGINE!A61="","",SUMMARY_ENGINE!A61),"") | B69: =IFERROR(IF(SUMMARY_ENGINE!A61="","",SUMMARY_ENGINE!C61),"") | C69: =IFERROR(SUMMARY_ENGINE!E61,0) -> 0 | D69: =IFERROR(SUMMARY_ENGINE!F61,0) -> 0 | E69: =IFERROR(SUMMARY_ENGINE!I61,0) -> 0 | F69: =IFERROR(SUMMARY_ENGINE!H61,0) -> 0 | G69: =IFERROR(SUMMARY_ENGINE!J61,0) -> 0 | H69: =IFERROR(SUMMARY_ENGINE!K61,0) -> 0 | I69: =IFERROR(SUMMARY_ENGINE!M61,0) -> 0 | J69: =IFERROR(SUMMARY_ENGINE!N61,"—") -> —
... A211: =IFERROR(IF(SUMMARY_ENGINE!A203="","",SUMMARY_ENGINE!A203),"") | B211: =IFERROR(IF(SUMMARY_ENGINE!A203="","",SUMMARY_ENGINE!C203),"") | C211: =IFERROR(SUMMARY_ENGINE!E203,0) -> 0 | D211: =IFERROR(SUMMARY_ENGINE!F203,0) -> 0 | E211: =IFERROR(SUMMARY_ENGINE!I203,0) -> 0 | F211: =IFERROR(SUMMARY_ENGINE!H203,0) -> 0 | G211: =IFERROR(SUMMARY_ENGINE!J203,0) -> 0 | H211: =IFERROR(SUMMARY_ENGINE!K203,0) -> 0 | I211: =IFERROR(SUMMARY_ENGINE!M203,0) -> 0 | J211: =IFERROR(SUMMARY_ENGINE!N203,"—") -> —

Sheet PRODUK
A1: ◆ DATABASE PRODUK · Sumber Data Produk Tunggal ◆
A2: BIRU = isi manual · EMAS = formula otomatis · Tambah produk baru = tambah baris di bawah baris data terakhir
A3: PRODUCT_ID | B3: NAMA PRODUK | C3: KATEGORI | D3: SIZE RANGE | E3: TARGET HPP (Rp) | F3: HARGA JUAL (Rp) | G3: MARGIN TARGET % | H3: KETERANGAN / STATUS
A4: PRD-001 | B4: Abaya Premium Linen | C4: Abaya | D4: S,M,L,XL | E4: 185000 | F4: 350000 | G4: =IFERROR(IF(AND(F4>0,E4>0),(F4-E4)/F4,IF(F4>0,1,0)),0) -> 0.47142857 | H4: =IFERROR(IF(B4<>"","Active","Inactive"),"") -> Active
A5: PRD-002 | B5: Gamis Velvet Bordir | C5: Gamis | D5: S,M,L,XL,XXL | E5: 220000 | F5: 450000 | G5: =IFERROR(IF(AND(F5>0,E5>0),(F5-E5)/F5,IF(F5>0,1,0)),0) -> 0.51111111 | H5: =IFERROR(IF(B5<>"","Active","Inactive"),"") -> Active
A6: PRD-003 | B6: Kaftan Silk Premium | C6: Kaftan | D6: Free Size | E6: 280000 | F6: 580000 | G6: =IFERROR(IF(AND(F6>0,E6>0),(F6-E6)/F6,IF(F6>0,1,0)),0) -> 0.51724138 | H6: =IFERROR(IF(B6<>"","Active","Inactive"),"") -> Active
A7: PRD-004 | B7: Tunik Casual Linen | C7: Tunik | D7: S,M,L,XL | E7: 110000 | F7: 225000 | G7: =IFERROR(IF(AND(F7>0,E7>0),(F7-E7)/F7,IF(F7>0,1,0)),0) -> 0.51111111 | H7: =IFERROR(IF(B7<>"","Active","Inactive"),"") -> Active
A8: PRD-005 | B8: Dress Batik Modern | C8: Dress | D8: S,M,L,XL | E8: 150000 | F8: 285000 | G8: =IFERROR(IF(AND(F8>0,E8>0),(F8-E8)/F8,IF(F8>0,1,0)),0) -> 0.47368421 | H8: =IFERROR(IF(B8<>"","Active","Inactive"),"") -> Active
A9: PRD-006 | G9: =IFERROR(IF(AND(F9>0,E9>0),(F9-E9)/F9,IF(F9>0,1,0)),0) -> 0 | H9: =IFERROR(IF(B9<>"","Active","Inactive"),"") -> Inactive
A10: PRD-007 | G10: =IFERROR(IF(AND(F10>0,E10>0),(F10-E10)/F10,IF(F10>0,1,0)),0) -> 0 | H10: =IFERROR(IF(B10<>"","Active","Inactive"),"") -> Inactive
A11: PRD-008 | G11: =IFERROR(IF(AND(F11>0,E11>0),(F11-E11)/F11,IF(F11>0,1,0)),0) -> 0 | H11: =IFERROR(IF(B11<>"","Active","Inactive"),"") -> Inactive
A12: PRD-009 | G12: =IFERROR(IF(AND(F12>0,E12>0),(F12-E12)/F12,IF(F12>0,1,0)),0) -> 0 | H12: =IFERROR(IF(B12<>"","Active","Inactive"),"") -> Inactive
A13: PRD-010 | G13: =IFERROR(IF(AND(F13>0,E13>0),(F13-E13)/F13,IF(F13>0,1,0)),0) -> 0 | H13: =IFERROR(IF(B13<>"","Active","Inactive"),"") -> Inactive
A14: PRD-011 | G14: =IFERROR(IF(AND(F14>0,E14>0),(F14-E14)/F14,IF(F14>0,1,0)),0) -> 0 | H14: =IFERROR(IF(B14<>"","Active","Inactive"),"") -> Inactive
A15: PRD-012 | G15: =IFERROR(IF(AND(F15>0,E15>0),(F15-E15)/F15,IF(F15>0,1,0)),0) -> 0 | H15: =IFERROR(IF(B15<>"","Active","Inactive"),"") -> Inactive
A16: PRD-013 | G16: =IFERROR(IF(AND(F16>0,E16>0),(F16-E16)/F16,IF(F16>0,1,0)),0) -> 0 | H16: =IFERROR(IF(B16<>"","Active","Inactive"),"") -> Inactive
A17: PRD-014 | G17: =IFERROR(IF(AND(F17>0,E17>0),(F17-E17)/F17,IF(F17>0,1,0)),0) -> 0 | H17: =IFERROR(IF(B17<>"","Active","Inactive"),"") -> Inactive
A18: PRD-015 | G18: =IFERROR(IF(AND(F18>0,E18>0),(F18-E18)/F18,IF(F18>0,1,0)),0) -> 0 | H18: =IFERROR(IF(B18<>"","Active","Inactive"),"") -> Inactive
A19: PRD-016 | G19: =IFERROR(IF(AND(F19>0,E19>0),(F19-E19)/F19,IF(F19>0,1,0)),0) -> 0 | H19: =IFERROR(IF(B19<>"","Active","Inactive"),"") -> Inactive
A20: PRD-017 | G20: =IFERROR(IF(AND(F20>0,E20>0),(F20-E20)/F20,IF(F20>0,1,0)),0) -> 0 | H20: =IFERROR(IF(B20<>"","Active","Inactive"),"") -> Inactive
... A52: PRD-049 | G52: =IFERROR(IF(AND(F52>0,E52>0),(F52-E52)/F52,IF(F52>0,1,0)),0) -> 0 | H52: =IFERROR(IF(B52<>"","Active","Inactive"),"") -> Inactive

Sheet MATERIAL
A1: ◆ DATABASE MATERIAL · Bahan Baku & Supplier ◆
A2: BIRU = isi manual · Status: Active / Inactive / Discontinue · Harga dipakai untuk estimasi kebutuhan material
A3: MATERIAL_ID | B3: NAMA MATERIAL | C3: SATUAN | D3: HARGA/UNIT (Rp) | E3: SUPPLIER | F3: LEAD TIME | G3: STATUS | H3: CATATAN
A4: MAT-001 | B4: Kain Linen Premium | C4: meter | D4: 45000 | E4: CV Tekstil Nusantara | F4: 3-5 hari | G4: Active
A5: MAT-002 | B5: Kain Velvet | C5: meter | D5: 85000 | E5: PT Kain Jaya | F5: 5-7 hari | G5: Active
A6: MAT-003 | B6: Kain Silk Satin | C6: meter | D6: 120000 | E6: CV Mitra Silk | F6: 7-10 hari | G6: Active
A7: MAT-004 | B7: Kain Batik Premium | C7: meter | D7: 95000 | E7: Batik Larasati | F7: 3-5 hari | G7: Active
A8: MAT-005 | B8: Benang Bordir | C8: gulung | D8: 12000 | E8: Toko Benang Raya | F8: 1-2 hari | G8: Active
A9: MAT-006 | B9: Kancing Premium | C9: set | D9: 8500 | E9: CV Aksesori Indah | F9: 2-3 hari | G9: Active
A10: MAT-007 | B10: Resleting YKK | C10: pcs | D10: 4500 | E10: Toko YKK | F10: 1-2 hari | G10: Active
A11: MAT-008 | G11: Inactive
A12: MAT-009 | G12: Inactive
A13: MAT-010 | G13: Inactive
A14: MAT-011 | G14: Inactive
A15: MAT-012 | G15: Inactive
A16: MAT-013 | G16: Inactive
A17: MAT-014 | G17: Inactive
A18: MAT-015 | G18: Inactive
A19: MAT-016 | G19: Inactive
A20: MAT-017 | G20: Inactive
A21: MAT-018 | G21: Inactive
A22: MAT-019 | G22: Inactive
... A52: MAT-049 | G52: Inactive

Sheet PARAMETER
A1: ◆ PARAMETER SISTEM · Konfigurasi Global ◆
A2: ⚠ UBAH KOLOM NILAI (B) SAJA · Mengubah posisi baris akan merusak seluruh sistem
A3: ⚠ PERINGATAN KERAS: Semua sheet engine mereferensi parameter ini via Named Range. Geser baris = sistem rusak!
A4: NAMED RANGE (ID) | B4: NILAI | C4: FORMAT | D4: KETERANGAN LENGKAP | E4: BERLAKU DI SHEET
A5: PARAM_REJECT_MAX | B5: 0.05 | C5: 0.0% | D5: Reject rate MAKSIMAL per batch — Alert ⚠ PERHATIAN jika melebihi batas ini. Dipakai PRODUCTION_PLAN & AI_ANALYSIS untuk status QC. | E5: PRODUCTION_PLAN, AI_ANALYSIS
A6: PARAM_REJECT_MAJOR | B6: 0.02 | C6: 0.0% | D6: Reject MAJOR per batch — Alert eskalasi merah jika melebihi. Reject major = cacat struktural/tidak bisa diperbaiki. | E6: PRODUCTION_PLAN
A7: PARAM_MARGIN_TARGET | B7: 0.4 | C7: 0.0% | D7: Target gross margin MINIMUM per order — KPI utama profitabilitas. Order di bawah ini masuk kategori review harga & HPP. | E7: HPP_ENGINE, AI_ANALYSIS, DASHBOARD
A8: PARAM_MARGIN_WARNING | B8: 0.15 | C8: 0.0% | D8: Batas bawah margin — jika margin aktual di bawah ini, status berubah TIPIS / WARNING merah. Perlu eskalasi segera ke manajemen. | E8: HPP_ENGINE, AI_ANALYSIS
A9: PARAM_OVERHEAD_PCT | B9: 0.1 | C9: 0.0% | D9: Overhead % dari (Biaya Bahan + TK). Biaya operasional umum: listrik, air, sewa, admin. Ubah jika kondisi bisnis berubah. | E9: HPP_ENGINE
A10: PARAM_HPP_TIPIS | B10: 0.05 | C10: 0.0% | D10: Toleransi HPP tipis — HPP aktual boleh melebihi target HPP hingga % ini tanpa alert. Di luar toleransi → status ⚠ MAHAL. | E10: HPP_ENGINE
A11: PARAM_PCT_JEEHANA | B11: 0.4 | C11: 0% | D11: Persentase distribusi net profit untuk Jeehana. Harus total Jeehana + Hasan + Kas = 100%. | E11: AI_ANALYSIS
A12: PARAM_PCT_HASAN | B12: 0.3 | C12: 0% | D12: Persentase distribusi net profit untuk Hasan. Ubah sesuai kesepakatan bagi hasil terbaru. | E12: AI_ANALYSIS
A13: PARAM_PCT_KAS | B13: =IFERROR(1-B11-B12,0) -> 0.3 | C13: 0% | D13: Persentase distribusi net profit ke Kas Usaha (reinvestasi). Formula: = 1 - Jeehana - Hasan. Otomatis jika di-set manual = 1-B9-B10. | E13: AI_ANALYSIS
A15: ◈ VALIDASI DISTRIBUSI PROFIT (Jeehana + Hasan + Kas harus = 100%)
A16: =IF(ABS(B11+B12+B13-1)<0.001,"✅ DISTRIBUSI VALID — Total = 100%","🚨 ERROR: Total = "&TEXT(B11+B12+B13,"0%")&" — Harus tepat 100%!") -> ✅ DISTRIBUSI VALID — Total = 100%

Sheet HPP_ENGINE
A1: ◆ HPP ENGINE · Harga Pokok Produksi Per Order ◆
A2: BIRU = isi manual (ORDER_ID, PRODUCT_ID, QTY, Biaya Bahan, TK, QC) · EMAS = formula otomatis · Kapasitas: 200 order
A3: ORDER_ID | B3: PRODUCT_ID | C3: NAMA PRODUK | D3: QTY PROD | E3: BIAYA BAHAN (Rp) | F3: BIAYA TK (Rp) | G3: BIAYA QC (Rp) | H3: OVERHEAD (Rp) | I3: TOTAL COST (Rp) | J3: HPP/PCS (Rp) | K3: TARGET HPP (Rp) | L3: SELISIH HPP (Rp) | M3: STATUS HPP
A4: HZN-2604-001 | B4: PRD-001 | C4: {=IFERROR(IF(B4="","",INDEX(PRODUK!$B:$B,MATCH(B4,PRODUK!$A:$A,0))),"")} -> Abaya Premium Linen | D4: 148 | E4: 22000000 | F4: 3330000 | G4: 890000 | H4: =IFERROR(IF(A4="",0,(E4+F4)*PARAM_OVERHEAD_PCT),0) -> 2533000 | I4: =IFERROR(IF(A4="",0,E4+F4+G4+H4),0) -> 28753000 | J4: =IFERROR(IF(OR(A4="",D4=0),0,I4/D4),0) -> 194277.03 | K4: {=IFERROR(IF(B4="",0,INDEX(PRODUK!$E:$E,MATCH(B4,PRODUK!$A:$A,0))),0)} -> 185000 | L4: =IFERROR(IF(A4="","—",IF(K4=0,"—",K4-J4)),"—") -> -9277.027 | M4: =IFERROR(IF(A4="","—",IF(D4=0,"—",IF(J4=0,"—",IF(J4<=K4,"✓ OK",IF(J4<=K4*(1+PARAM_HPP_TIPIS),"⚠ TIPIS","⚠ MAHAL"))))), "—") -> ⚠ MAHAL
A5: HZN-2604-002 | B5: PRD-002 | C5: {=IFERROR(IF(B5="","",INDEX(PRODUK!$B:$B,MATCH(B5,PRODUK!$A:$A,0))),"")} -> Gamis Velvet Bordir | D5: 185 | E5: 35000000 | F5: 5280000 | G5: 1320000 | H5: =IFERROR(IF(A5="",0,(E5+F5)*PARAM_OVERHEAD_PCT),0) -> 4028000 | I5: =IFERROR(IF(A5="",0,E5+F5+G5+H5),0) -> 45628000 | J5: =IFERROR(IF(OR(A5="",D5=0),0,I5/D5),0) -> 246637.84 | K5: {=IFERROR(IF(B5="",0,INDEX(PRODUK!$E:$E,MATCH(B5,PRODUK!$A:$A,0))),0)} -> 220000 | L5: =IFERROR(IF(A5="","—",IF(K5=0,"—",K5-J5)),"—") -> -26637.838 | M5: =IFERROR(IF(A5="","—",IF(D5=0,"—",IF(J5=0,"—",IF(J5<=K5,"✓ OK",IF(J5<=K5*(1+PARAM_HPP_TIPIS),"⚠ TIPIS","⚠ MAHAL"))))), "—") -> ⚠ MAHAL
A6: HZN-2604-003 | B6: PRD-003 | C6: {=IFERROR(IF(B6="","",INDEX(PRODUK!$B:$B,MATCH(B6,PRODUK!$A:$A,0))),"")} -> Kaftan Silk Premium | D6: 80 | E6: 16800000 | F6: 2720000 | G6: 680000 | H6: =IFERROR(IF(A6="",0,(E6+F6)*PARAM_OVERHEAD_PCT),0) -> 1952000 | I6: =IFERROR(IF(A6="",0,E6+F6+G6+H6),0) -> 22152000 | J6: =IFERROR(IF(OR(A6="",D6=0),0,I6/D6),0) -> 276900 | K6: {=IFERROR(IF(B6="",0,INDEX(PRODUK!$E:$E,MATCH(B6,PRODUK!$A:$A,0))),0)} -> 280000 | L6: =IFERROR(IF(A6="","—",IF(K6=0,"—",K6-J6)),"—") -> 3100 | M6: =IFERROR(IF(A6="","—",IF(D6=0,"—",IF(J6=0,"—",IF(J6<=K6,"✓ OK",IF(J6<=K6*(1+PARAM_HPP_TIPIS),"⚠ TIPIS","⚠ MAHAL"))))), "—") -> ✓ OK
A7: HZN-2604-004 | B7: PRD-004 | C7: {=IFERROR(IF(B7="","",INDEX(PRODUK!$B:$B,MATCH(B7,PRODUK!$A:$A,0))),"")} -> Tunik Casual Linen | D7: 120 | E7: 11040000 | F7: 2040000 | G7: 510000 | H7: =IFERROR(IF(A7="",0,(E7+F7)*PARAM_OVERHEAD_PCT),0) -> 1308000 | I7: =IFERROR(IF(A7="",0,E7+F7+G7+H7),0) -> 14898000 | J7: =IFERROR(IF(OR(A7="",D7=0),0,I7/D7),0) -> 124150 | K7: {=IFERROR(IF(B7="",0,INDEX(PRODUK!$E:$E,MATCH(B7,PRODUK!$A:$A,0))),0)} -> 110000 | L7: =IFERROR(IF(A7="","—",IF(K7=0,"—",K7-J7)),"—") -> -14150 | M7: =IFERROR(IF(A7="","—",IF(D7=0,"—",IF(J7=0,"—",IF(J7<=K7,"✓ OK",IF(J7<=K7*(1+PARAM_HPP_TIPIS),"⚠ TIPIS","⚠ MAHAL"))))), "—") -> ⚠ MAHAL
A8: HZN-2604-005 | B8: PRD-005 | C8: {=IFERROR(IF(B8="","",INDEX(PRODUK!$B:$B,MATCH(B8,PRODUK!$A:$A,0))),"")} -> Dress Batik Modern | D8: 50 | E8: 10000000 | F8: 4000000 | G8: 400000 | H8: =IFERROR(IF(A8="",0,(E8+F8)*PARAM_OVERHEAD_PCT),0) -> 1400000 | I8: =IFERROR(IF(A8="",0,E8+F8+G8+H8),0) -> 15800000 | J8: =IFERROR(IF(OR(A8="",D8=0),0,I8/D8),0) -> 316000 | K8: {=IFERROR(IF(B8="",0,INDEX(PRODUK!$E:$E,MATCH(B8,PRODUK!$A:$A,0))),0)} -> 150000 | L8: =IFERROR(IF(A8="","—",IF(K8=0,"—",K8-J8)),"—") -> -166000 | M8: =IFERROR(IF(A8="","—",IF(D8=0,"—",IF(J8=0,"—",IF(J8<=K8,"✓ OK",IF(J8<=K8*(1+PARAM_HPP_TIPIS),"⚠ TIPIS","⚠ MAHAL"))))), "—") -> ⚠ MAHAL
A9: HZN-2604-006 | B9: PRD-001 | C9: {=IFERROR(IF(B9="","",INDEX(PRODUK!$B:$B,MATCH(B9,PRODUK!$A:$A,0))),"")} -> Abaya Premium Linen | D9: 240 | E9: 36750000 | F9: 5400000 | G9: 1350000 | H9: =IFERROR(IF(A9="",0,(E9+F9)*PARAM_OVERHEAD_PCT),0) -> 4215000 | I9: =IFERROR(IF(A9="",0,E9+F9+G9+H9),0) -> 47715000 | J9: =IFERROR(IF(OR(A9="",D9=0),0,I9/D9),0) -> 198812.5 | K9: {=IFERROR(IF(B9="",0,INDEX(PRODUK!$E:$E,MATCH(B9,PRODUK!$A:$A,0))),0)} -> 185000 | L9: =IFERROR(IF(A9="","—",IF(K9=0,"—",K9-J9)),"—") -> -13812.5 | M9: =IFERROR(IF(A9="","—",IF(D9=0,"—",IF(J9=0,"—",IF(J9<=K9,"✓ OK",IF(J9<=K9*(1+PARAM_HPP_TIPIS),"⚠ TIPIS","⚠ MAHAL"))))), "—") -> ⚠ MAHAL
A10: HZN-2604-007 | B10: PRD-002 | C10: {=IFERROR(IF(B10="","",INDEX(PRODUK!$B:$B,MATCH(B10,PRODUK!$A:$A,0))),"")} -> Gamis Velvet Bordir | D10: 170 | E10: 31450000 | F10: 4760000 | G10: 1190000 | H10: =IFERROR(IF(A10="",0,(E10+F10)*PARAM_OVERHEAD_PCT),0) -> 3621000 | I10: =IFERROR(IF(A10="",0,E10+F10+G10+H10),0) -> 41021000 | J10: =IFERROR(IF(OR(A10="",D10=0),0,I10/D10),0) -> 241300 | K10: {=IFERROR(IF(B10="",0,INDEX(PRODUK!$E:$E,MATCH(B10,PRODUK!$A:$A,0))),0)} -> 220000 | L10: =IFERROR(IF(A10="","—",IF(K10=0,"—",K10-J10)),"—") -> -21300 | M10: =IFERROR(IF(A10="","—",IF(D10=0,"—",IF(J10=0,"—",IF(J10<=K10,"✓ OK",IF(J10<=K10*(1+PARAM_HPP_TIPIS),"⚠ TIPIS","⚠ MAHAL"))))), "—") -> ⚠ MAHAL
C11: {=IFERROR(IF(B11="","",INDEX(PRODUK!$B:$B,MATCH(B11,PRODUK!$A:$A,0))),"")} | H11: =IFERROR(IF(A11="",0,(E11+F11)*PARAM_OVERHEAD_PCT),0) -> 0 | I11: =IFERROR(IF(A11="",0,E11+F11+G11+H11),0) -> 0 | J11: =IFERROR(IF(OR(A11="",D11=0),0,I11/D11),0) -> 0 | K11: {=IFERROR(IF(B11="",0,INDEX(PRODUK!$E:$E,MATCH(B11,PRODUK!$A:$A,0))),0)} -> 0 | L11: =IFERROR(IF(A11="","—",IF(K11=0,"—",K11-J11)),"—") -> — | M11: =IFERROR(IF(A11="","—",IF(D11=0,"—",IF(J11=0,"—",IF(J11<=K11,"✓ OK",IF(J11<=K11*(1+PARAM_HPP_TIPIS),"⚠ TIPIS","⚠ MAHAL"))))), "—") -> —
C12: {=IFERROR(IF(B12="","",INDEX(PRODUK!$B:$B,MATCH(B12,PRODUK!$A:$A,0))),"")} | H12: =IFERROR(IF(A12="",0,(E12+F12)*PARAM_OVERHEAD_PCT),0) -> 0 | I12: =IFERROR(IF(A12="",0,E12+F12+G12+H12),0) -> 0 | J12: =IFERROR(IF(OR(A12="",D12=0),0,I12/D12),0) -> 0 | K12: {=IFERROR(IF(B12="",0,INDEX(PRODUK!$E:$E,MATCH(B12,PRODUK!$A:$A,0))),0)} -> 0 | L12: =IFERROR(IF(A12="","—",IF(K12=0,"—",K12-J12)),"—") -> — | M12: =IFERROR(IF(A12="","—",IF(D12=0,"—",IF(J12=0,"—",IF(J12<=K12,"✓ OK",IF(J12<=K12*(1+PARAM_HPP_TIPIS),"⚠ TIPIS","⚠ MAHAL"))))), "—") -> —
C13: {=IFERROR(IF(B13="","",INDEX(PRODUK!$B:$B,MATCH(B13,PRODUK!$A:$A,0))),"")} | H13: =IFERROR(IF(A13="",0,(E13+F13)*PARAM_OVERHEAD_PCT),0) -> 0 | I13: =IFERROR(IF(A13="",0,E13+F13+G13+H13),0) -> 0 | J13: =IFERROR(IF(OR(A13="",D13=0),0,I13/D13),0) -> 0 | K13: {=IFERROR(IF(B13="",0,INDEX(PRODUK!$E:$E,MATCH(B13,PRODUK!$A:$A,0))),0)} -> 0 | L13: =IFERROR(IF(A13="","—",IF(K13=0,"—",K13-J13)),"—") -> — | M13: =IFERROR(IF(A13="","—",IF(D13=0,"—",IF(J13=0,"—",IF(J13<=K13,"✓ OK",IF(J13<=K13*(1+PARAM_HPP_TIPIS),"⚠ TIPIS","⚠ MAHAL"))))), "—") -> —
C14: {=IFERROR(IF(B14="","",INDEX(PRODUK!$B:$B,MATCH(B14,PRODUK!$A:$A,0))),"")} | H14: =IFERROR(IF(A14="",0,(E14+F14)*PARAM_OVERHEAD_PCT),0) -> 0 | I14: =IFERROR(IF(A14="",0,E14+F14+G14+H14),0) -> 0 | J14: =IFERROR(IF(OR(A14="",D14=0),0,I14/D14),0) -> 0 | K14: {=IFERROR(IF(B14="",0,INDEX(PRODUK!$E:$E,MATCH(B14,PRODUK!$A:$A,0))),0)} -> 0 | L14: =IFERROR(IF(A14="","—",IF(K14=0,"—",K14-J14)),"—") -> — | M14: =IFERROR(IF(A14="","—",IF(D14=0,"—",IF(J14=0,"—",IF(J14<=K14,"✓ OK",IF(J14<=K14*(1+PARAM_HPP_TIPIS),"⚠ TIPIS","⚠ MAHAL"))))), "—") -> —
C15: {=IFERROR(IF(B15="","",INDEX(PRODUK!$B:$B,MATCH(B15,PRODUK!$A:$A,0))),"")} | H15: =IFERROR(IF(A15="",0,(E15+F15)*PARAM_OVERHEAD_PCT),0) -> 0 | I15: =IFERROR(IF(A15="",0,E15+F15+G15+H15),0) -> 0 | J15: =IFERROR(IF(OR(A15="",D15=0),0,I15/D15),0) -> 0 | K15: {=IFERROR(IF(B15="",0,INDEX(PRODUK!$E:$E,MATCH(B15,PRODUK!$A:$A,0))),0)} -> 0 | L15: =IFERROR(IF(A15="","—",IF(K15=0,"—",K15-J15)),"—") -> — | M15: =IFERROR(IF(A15="","—",IF(D15=0,"—",IF(J15=0,"—",IF(J15<=K15,"✓ OK",IF(J15<=K15*(1+PARAM_HPP_TIPIS),"⚠ TIPIS","⚠ MAHAL"))))), "—") -> —
C16: {=IFERROR(IF(B16="","",INDEX(PRODUK!$B:$B,MATCH(B16,PRODUK!$A:$A,0))),"")} | H16: =IFERROR(IF(A16="",0,(E16+F16)*PARAM_OVERHEAD_PCT),0) -> 0 | I16: =IFERROR(IF(A16="",0,E16+F16+G16+H16),0) -> 0 | J16: =IFERROR(IF(OR(A16="",D16=0),0,I16/D16),0) -> 0 | K16: {=IFERROR(IF(B16="",0,INDEX(PRODUK!$E:$E,MATCH(B16,PRODUK!$A:$A,0))),0)} -> 0 | L16: =IFERROR(IF(A16="","—",IF(K16=0,"—",K16-J16)),"—") -> — | M16: =IFERROR(IF(A16="","—",IF(D16=0,"—",IF(J16=0,"—",IF(J16<=K16,"✓ OK",IF(J16<=K16*(1+PARAM_HPP_TIPIS),"⚠ TIPIS","⚠ MAHAL"))))), "—") -> —
C17: {=IFERROR(IF(B17="","",INDEX(PRODUK!$B:$B,MATCH(B17,PRODUK!$A:$A,0))),"")} | H17: =IFERROR(IF(A17="",0,(E17+F17)*PARAM_OVERHEAD_PCT),0) -> 0 | I17: =IFERROR(IF(A17="",0,E17+F17+G17+H17),0) -> 0 | J17: =IFERROR(IF(OR(A17="",D17=0),0,I17/D17),0) -> 0 | K17: {=IFERROR(IF(B17="",0,INDEX(PRODUK!$E:$E,MATCH(B17,PRODUK!$A:$A,0))),0)} -> 0 | L17: =IFERROR(IF(A17="","—",IF(K17=0,"—",K17-J17)),"—") -> — | M17: =IFERROR(IF(A17="","—",IF(D17=0,"—",IF(J17=0,"—",IF(J17<=K17,"✓ OK",IF(J17<=K17*(1+PARAM_HPP_TIPIS),"⚠ TIPIS","⚠ MAHAL"))))), "—") -> —
C18: {=IFERROR(IF(B18="","",INDEX(PRODUK!$B:$B,MATCH(B18,PRODUK!$A:$A,0))),"")} | H18: =IFERROR(IF(A18="",0,(E18+F18)*PARAM_OVERHEAD_PCT),0) -> 0 | I18: =IFERROR(IF(A18="",0,E18+F18+G18+H18),0) -> 0 | J18: =IFERROR(IF(OR(A18="",D18=0),0,I18/D18),0) -> 0 | K18: {=IFERROR(IF(B18="",0,INDEX(PRODUK!$E:$E,MATCH(B18,PRODUK!$A:$A,0))),0)} -> 0 | L18: =IFERROR(IF(A18="","—",IF(K18=0,"—",K18-J18)),"—") -> — | M18: =IFERROR(IF(A18="","—",IF(D18=0,"—",IF(J18=0,"—",IF(J18<=K18,"✓ OK",IF(J18<=K18*(1+PARAM_HPP_TIPIS),"⚠ TIPIS","⚠ MAHAL"))))), "—") -> —
C19: {=IFERROR(IF(B19="","",INDEX(PRODUK!$B:$B,MATCH(B19,PRODUK!$A:$A,0))),"")} | H19: =IFERROR(IF(A19="",0,(E19+F19)*PARAM_OVERHEAD_PCT),0) -> 0 | I19: =IFERROR(IF(A19="",0,E19+F19+G19+H19),0) -> 0 | J19: =IFERROR(IF(OR(A19="",D19=0),0,I19/D19),0) -> 0 | K19: {=IFERROR(IF(B19="",0,INDEX(PRODUK!$E:$E,MATCH(B19,PRODUK!$A:$A,0))),0)} -> 0 | L19: =IFERROR(IF(A19="","—",IF(K19=0,"—",K19-J19)),"—") -> — | M19: =IFERROR(IF(A19="","—",IF(D19=0,"—",IF(J19=0,"—",IF(J19<=K19,"✓ OK",IF(J19<=K19*(1+PARAM_HPP_TIPIS),"⚠ TIPIS","⚠ MAHAL"))))), "—") -> —
C20: {=IFERROR(IF(B20="","",INDEX(PRODUK!$B:$B,MATCH(B20,PRODUK!$A:$A,0))),"")} | H20: =IFERROR(IF(A20="",0,(E20+F20)*PARAM_OVERHEAD_PCT),0) -> 0 | I20: =IFERROR(IF(A20="",0,E20+F20+G20+H20),0) -> 0 | J20: =IFERROR(IF(OR(A20="",D20=0),0,I20/D20),0) -> 0 | K20: {=IFERROR(IF(B20="",0,INDEX(PRODUK!$E:$E,MATCH(B20,PRODUK!$A:$A,0))),0)} -> 0 | L20: =IFERROR(IF(A20="","—",IF(K20=0,"—",K20-J20)),"—") -> — | M20: =IFERROR(IF(A20="","—",IF(D20=0,"—",IF(J20=0,"—",IF(J20<=K20,"✓ OK",IF(J20<=K20*(1+PARAM_HPP_TIPIS),"⚠ TIPIS","⚠ MAHAL"))))), "—") -> —
C21: {=IFERROR(IF(B21="","",INDEX(PRODUK!$B:$B,MATCH(B21,PRODUK!$A:$A,0))),"")} | H21: =IFERROR(IF(A21="",0,(E21+F21)*PARAM_OVERHEAD_PCT),0) -> 0 | I21: =IFERROR(IF(A21="",0,E21+F21+G21+H21),0) -> 0 | J21: =IFERROR(IF(OR(A21="",D21=0),0,I21/D21),0) -> 0 | K21: {=IFERROR(IF(B21="",0,INDEX(PRODUK!$E:$E,MATCH(B21,PRODUK!$A:$A,0))),0)} -> 0 | L21: =IFERROR(IF(A21="","—",IF(K21=0,"—",K21-J21)),"—") -> — | M21: =IFERROR(IF(A21="","—",IF(D21=0,"—",IF(J21=0,"—",IF(J21<=K21,"✓ OK",IF(J21<=K21*(1+PARAM_HPP_TIPIS),"⚠ TIPIS","⚠ MAHAL"))))), "—") -> —
C22: {=IFERROR(IF(B22="","",INDEX(PRODUK!$B:$B,MATCH(B22,PRODUK!$A:$A,0))),"")} | H22: =IFERROR(IF(A22="",0,(E22+F22)*PARAM_OVERHEAD_PCT),0) -> 0 | I22: =IFERROR(IF(A22="",0,E22+F22+G22+H22),0) -> 0 | J22: =IFERROR(IF(OR(A22="",D22=0),0,I22/D22),0) -> 0 | K22: {=IFERROR(IF(B22="",0,INDEX(PRODUK!$E:$E,MATCH(B22,PRODUK!$A:$A,0))),0)} -> 0 | L22: =IFERROR(IF(A22="","—",IF(K22=0,"—",K22-J22)),"—") -> — | M22: =IFERROR(IF(A22="","—",IF(D22=0,"—",IF(J22=0,"—",IF(J22<=K22,"✓ OK",IF(J22<=K22*(1+PARAM_HPP_TIPIS),"⚠ TIPIS","⚠ MAHAL"))))), "—") -> —
... C203: {=IFERROR(IF(B203="","",INDEX(PRODUK!$B:$B,MATCH(B203,PRODUK!$A:$A,0))),"")} | H203: =IFERROR(IF(A203="",0,(E203+F203)*PARAM_OVERHEAD_PCT),0) -> 0 | I203: =IFERROR(IF(A203="",0,E203+F203+G203+H203),0) -> 0 | J203: =IFERROR(IF(OR(A203="",D203=0),0,I203/D203),0) -> 0 | K203: {=IFERROR(IF(B203="",0,INDEX(PRODUK!$E:$E,MATCH(B203,PRODUK!$A:$A,0))),0)} -> 0 | L203: =IFERROR(IF(A203="","—",IF(K203=0,"—",K203-J203)),"—") -> — | M203: =IFERROR(IF(A203="","—",IF(D203=0,"—",IF(J203=0,"—",IF(J203<=K203,"✓ OK",IF(J203<=K203*(1+PARAM_HPP_TIPIS),"⚠ TIPIS","⚠ MAHAL"))))), "—") -> —

Sheet PRODUCTION_PLAN
A1: ◆ PRODUCTION PLAN · Target vs Realisasi · QC & Aging Real-Time ◆
A2: BIRU = isi manual (ORDER_ID, PRODUCT_ID, Klien, QTY, Tanggal, Status, Reject) · EMAS = formula otomatis · Kapasitas: 200 order
A3: ORDER_ID | B3: PRODUCT_ID | C3: NAMA KLIEN | D3: QTY PLAN | E3: QTY REALISASI | F3: TGL MULAI | G3: TGL SELESAI | H3: STATUS ORDER | I3: REJECT TOTAL | J3: REJECT RATE | K3: STATUS QC | L3: AGING (hari) | M3: SISA HARI
A4: HZN-2604-001 | B4: PRD-001 | C4: Elara Boutique | D4: 150 | E4: 148 | F4: 2026-03-27 | G4: 2026-04-14 | H4: Produksi | I4: 6 | J4: =IFERROR(IF(OR(A4="",E4=0),0,I4/E4),0) -> 0.040540541 | K4: =IFERROR(IF(A4="","—",IF(H4="Selesai","✓ Selesai",IF(H4="Cancel","✗ Cancel",IF(E4=0,"—",IF(J4=0,"✓ BAGUS",IF(J4<=PARAM_REJECT_MAJOR,"⚠ MINOR",IF(J4<=PARAM_REJECT_MAX,"⚠ PERHATIAN","🚨 ESKALASI"))))))), "—") -> ⚠ PERHATIAN | L4: =IFERROR(IF(A4="","—",IF(H4="Selesai","✓ Selesai",IF(H4="Cancel","✗ Cancel",IF(F4="","—",TODAY()-F4)))),"—") -> 17 | M4: =IFERROR(IF(A4="","—",IF(OR(H4="Selesai",H4="Cancel"),"✓ Done",IF(G4="","—",G4-TODAY()))),"—") -> 1
A5: HZN-2604-002 | B5: PRD-002 | C5: Atelier Nusantara | D5: 200 | E5: 185 | F5: 2026-03-31 | G5: 2026-04-20 | H5: Produksi | I5: 9 | J5: =IFERROR(IF(OR(A5="",E5=0),0,I5/E5),0) -> 0.048648649 | K5: =IFERROR(IF(A5="","—",IF(H5="Selesai","✓ Selesai",IF(H5="Cancel","✗ Cancel",IF(E5=0,"—",IF(J5=0,"✓ BAGUS",IF(J5<=PARAM_REJECT_MAJOR,"⚠ MINOR",IF(J5<=PARAM_REJECT_MAX,"⚠ PERHATIAN","🚨 ESKALASI"))))))), "—") -> ⚠ PERHATIAN | L5: =IFERROR(IF(A5="","—",IF(H5="Selesai","✓ Selesai",IF(H5="Cancel","✗ Cancel",IF(F5="","—",TODAY()-F5)))),"—") -> 13 | M5: =IFERROR(IF(A5="","—",IF(OR(H5="Selesai",H5="Cancel"),"✓ Done",IF(G5="","—",G5-TODAY()))),"—") -> 7
A6: HZN-2604-003 | B6: PRD-003 | C6: House of Laras | D6: 80 | E6: 80 | F6: 2026-04-03 | G6: 2026-04-28 | H6: Sample | I6: 3 | J6: =IFERROR(IF(OR(A6="",E6=0),0,I6/E6),0) -> 0.0375 | K6: =IFERROR(IF(A6="","—",IF(H6="Selesai","✓ Selesai",IF(H6="Cancel","✗ Cancel",IF(E6=0,"—",IF(J6=0,"✓ BAGUS",IF(J6<=PARAM_REJECT_MAJOR,"⚠ MINOR",IF(J6<=PARAM_REJECT_MAX,"⚠ PERHATIAN","🚨 ESKALASI"))))))), "—") -> ⚠ PERHATIAN | L6: =IFERROR(IF(A6="","—",IF(H6="Selesai","✓ Selesai",IF(H6="Cancel","✗ Cancel",IF(F6="","—",TODAY()-F6)))),"—") -> 10 | M6: =IFERROR(IF(A6="","—",IF(OR(H6="Selesai",H6="Cancel"),"✓ Done",IF(G6="","—",G6-TODAY()))),"—") -> 15
A7: HZN-2604-004 | B7: PRD-004 | C7: Butik Seruni | D7: 120 | E7: 120 | F7: 2026-03-21 | G7: 2026-04-07 | H7: Selesai | I7: 2 | J7: =IFERROR(IF(OR(A7="",E7=0),0,I7/E7),0) -> 0.016666667 | K7: =IFERROR(IF(A7="","—",IF(H7="Selesai","✓ Selesai",IF(H7="Cancel","✗ Cancel",IF(E7=0,"—",IF(J7=0,"✓ BAGUS",IF(J7<=PARAM_REJECT_MAJOR,"⚠ MINOR",IF(J7<=PARAM_REJECT_MAX,"⚠ PERHATIAN","🚨 ESKALASI"))))))), "—") -> ✓ Selesai | L7: =IFERROR(IF(A7="","—",IF(H7="Selesai","✓ Selesai",IF(H7="Cancel","✗ Cancel",IF(F7="","—",TODAY()-F7)))),"—") -> ✓ Selesai | M7: =IFERROR(IF(A7="","—",IF(OR(H7="Selesai",H7="Cancel"),"✓ Done",IF(G7="","—",G7-TODAY()))),"—") -> ✓ Done
A8: HZN-2604-005 | B8: PRD-005 | C8: Studio Raya | D8: 100 | E8: 20 | F8: 2026-04-07 | G8: 2026-05-02 | H8: Planning | I8: 1 | J8: =IFERROR(IF(OR(A8="",E8=0),0,I8/E8),0) -> 0.05 | K8: =IFERROR(IF(A8="","—",IF(H8="Selesai","✓ Selesai",IF(H8="Cancel","✗ Cancel",IF(E8=0,"—",IF(J8=0,"✓ BAGUS",IF(J8<=PARAM_REJECT_MAJOR,"⚠ MINOR",IF(J8<=PARAM_REJECT_MAX,"⚠ PERHATIAN","🚨 ESKALASI"))))))), "—") -> ⚠ PERHATIAN | L8: =IFERROR(IF(A8="","—",IF(H8="Selesai","✓ Selesai",IF(H8="Cancel","✗ Cancel",IF(F8="","—",TODAY()-F8)))),"—") -> 6 | M8: =IFERROR(IF(A8="","—",IF(OR(H8="Selesai",H8="Cancel"),"✓ Done",IF(G8="","—",G8-TODAY()))),"—") -> 19
A9: HZN-2604-006 | B9: PRD-001 | C9: CV Mitra Busana | D9: 250 | E9: 240 | F9: 2026-04-02 | G9: 2026-04-18 | H9: Produksi | I9: 8 | J9: =IFERROR(IF(OR(A9="",E9=0),0,I9/E9),0) -> 0.033333333 | K9: =IFERROR(IF(A9="","—",IF(H9="Selesai","✓ Selesai",IF(H9="Cancel","✗ Cancel",IF(E9=0,"—",IF(J9=0,"✓ BAGUS",IF(J9<=PARAM_REJECT_MAJOR,"⚠ MINOR",IF(J9<=PARAM_REJECT_MAX,"⚠ PERHATIAN","🚨 ESKALASI"))))))), "—") -> ⚠ PERHATIAN | L9: =IFERROR(IF(A9="","—",IF(H9="Selesai","✓ Selesai",IF(H9="Cancel","✗ Cancel",IF(F9="","—",TODAY()-F9)))),"—") -> 11 | M9: =IFERROR(IF(A9="","—",IF(OR(H9="Selesai",H9="Cancel"),"✓ Done",IF(G9="","—",G9-TODAY()))),"—") -> 5
A10: HZN-2604-007 | B10: PRD-002 | C10: Rumah Mode Sari | D10: 180 | E10: 170 | F10: 2026-04-05 | G10: 2026-04-25 | H10: Produksi | I10: 8 | J10: =IFERROR(IF(OR(A10="",E10=0),0,I10/E10),0) -> 0.047058824 | K10: =IFERROR(IF(A10="","—",IF(H10="Selesai","✓ Selesai",IF(H10="Cancel","✗ Cancel",IF(E10=0,"—",IF(J10=0,"✓ BAGUS",IF(J10<=PARAM_REJECT_MAJOR,"⚠ MINOR",IF(J10<=PARAM_REJECT_MAX,"⚠ PERHATIAN","🚨 ESKALASI"))))))), "—") -> ⚠ PERHATIAN | L10: =IFERROR(IF(A10="","—",IF(H10="Selesai","✓ Selesai",IF(H10="Cancel","✗ Cancel",IF(F10="","—",TODAY()-F10)))),"—") -> 8 | M10: =IFERROR(IF(A10="","—",IF(OR(H10="Selesai",H10="Cancel"),"✓ Done",IF(G10="","—",G10-TODAY()))),"—") -> 12
J11: =IFERROR(IF(OR(A11="",E11=0),0,I11/E11),0) -> 0 | K11: =IFERROR(IF(A11="","—",IF(H11="Selesai","✓ Selesai",IF(H11="Cancel","✗ Cancel",IF(E11=0,"—",IF(J11=0,"✓ BAGUS",IF(J11<=PARAM_REJECT_MAJOR,"⚠ MINOR",IF(J11<=PARAM_REJECT_MAX,"⚠ PERHATIAN","🚨 ESKALASI"))))))), "—") -> — | L11: =IFERROR(IF(A11="","—",IF(H11="Selesai","✓ Selesai",IF(H11="Cancel","✗ Cancel",IF(F11="","—",TODAY()-F11)))),"—") -> — | M11: =IFERROR(IF(A11="","—",IF(OR(H11="Selesai",H11="Cancel"),"✓ Done",IF(G11="","—",G11-TODAY()))),"—") -> —
J12: =IFERROR(IF(OR(A12="",E12=0),0,I12/E12),0) -> 0 | K12: =IFERROR(IF(A12="","—",IF(H12="Selesai","✓ Selesai",IF(H12="Cancel","✗ Cancel",IF(E12=0,"—",IF(J12=0,"✓ BAGUS",IF(J12<=PARAM_REJECT_MAJOR,"⚠ MINOR",IF(J12<=PARAM_REJECT_MAX,"⚠ PERHATIAN","🚨 ESKALASI"))))))), "—") -> — | L12: =IFERROR(IF(A12="","—",IF(H12="Selesai","✓ Selesai",IF(H12="Cancel","✗ Cancel",IF(F12="","—",TODAY()-F12)))),"—") -> — | M12: =IFERROR(IF(A12="","—",IF(OR(H12="Selesai",H12="Cancel"),"✓ Done",IF(G12="","—",G12-TODAY()))),"—") -> —
J13: =IFERROR(IF(OR(A13="",E13=0),0,I13/E13),0) -> 0 | K13: =IFERROR(IF(A13="","—",IF(H13="Selesai","✓ Selesai",IF(H13="Cancel","✗ Cancel",IF(E13=0,"—",IF(J13=0,"✓ BAGUS",IF(J13<=PARAM_REJECT_MAJOR,"⚠ MINOR",IF(J13<=PARAM_REJECT_MAX,"⚠ PERHATIAN","🚨 ESKALASI"))))))), "—") -> — | L13: =IFERROR(IF(A13="","—",IF(H13="Selesai","✓ Selesai",IF(H13="Cancel","✗ Cancel",IF(F13="","—",TODAY()-F13)))),"—") -> — | M13: =IFERROR(IF(A13="","—",IF(OR(H13="Selesai",H13="Cancel"),"✓ Done",IF(G13="","—",G13-TODAY()))),"—") -> —
J14: =IFERROR(IF(OR(A14="",E14=0),0,I14/E14),0) -> 0 | K14: =IFERROR(IF(A14="","—",IF(H14="Selesai","✓ Selesai",IF(H14="Cancel","✗ Cancel",IF(E14=0,"—",IF(J14=0,"✓ BAGUS",IF(J14<=PARAM_REJECT_MAJOR,"⚠ MINOR",IF(J14<=PARAM_REJECT_MAX,"⚠ PERHATIAN","🚨 ESKALASI"))))))), "—") -> — | L14: =IFERROR(IF(A14="","—",IF(H14="Selesai","✓ Selesai",IF(H14="Cancel","✗ Cancel",IF(F14="","—",TODAY()-F14)))),"—") -> — | M14: =IFERROR(IF(A14="","—",IF(OR(H14="Selesai",H14="Cancel"),"✓ Done",IF(G14="","—",G14-TODAY()))),"—") -> —
J15: =IFERROR(IF(OR(A15="",E15=0),0,I15/E15),0) -> 0 | K15: =IFERROR(IF(A15="","—",IF(H15="Selesai","✓ Selesai",IF(H15="Cancel","✗ Cancel",IF(E15=0,"—",IF(J15=0,"✓ BAGUS",IF(J15<=PARAM_REJECT_MAJOR,"⚠ MINOR",IF(J15<=PARAM_REJECT_MAX,"⚠ PERHATIAN","🚨 ESKALASI"))))))), "—") -> — | L15: =IFERROR(IF(A15="","—",IF(H15="Selesai","✓ Selesai",IF(H15="Cancel","✗ Cancel",IF(F15="","—",TODAY()-F15)))),"—") -> — | M15: =IFERROR(IF(A15="","—",IF(OR(H15="Selesai",H15="Cancel"),"✓ Done",IF(G15="","—",G15-TODAY()))),"—") -> —
J16: =IFERROR(IF(OR(A16="",E16=0),0,I16/E16),0) -> 0 | K16: =IFERROR(IF(A16="","—",IF(H16="Selesai","✓ Selesai",IF(H16="Cancel","✗ Cancel",IF(E16=0,"—",IF(J16=0,"✓ BAGUS",IF(J16<=PARAM_REJECT_MAJOR,"⚠ MINOR",IF(J16<=PARAM_REJECT_MAX,"⚠ PERHATIAN","🚨 ESKALASI"))))))), "—") -> — | L16: =IFERROR(IF(A16="","—",IF(H16="Selesai","✓ Selesai",IF(H16="Cancel","✗ Cancel",IF(F16="","—",TODAY()-F16)))),"—") -> — | M16: =IFERROR(IF(A16="","—",IF(OR(H16="Selesai",H16="Cancel"),"✓ Done",IF(G16="","—",G16-TODAY()))),"—") -> —
J17: =IFERROR(IF(OR(A17="",E17=0),0,I17/E17),0) -> 0 | K17: =IFERROR(IF(A17="","—",IF(H17="Selesai","✓ Selesai",IF(H17="Cancel","✗ Cancel",IF(E17=0,"—",IF(J17=0,"✓ BAGUS",IF(J17<=PARAM_REJECT_MAJOR,"⚠ MINOR",IF(J17<=PARAM_REJECT_MAX,"⚠ PERHATIAN","🚨 ESKALASI"))))))), "—") -> — | L17: =IFERROR(IF(A17="","—",IF(H17="Selesai","✓ Selesai",IF(H17="Cancel","✗ Cancel",IF(F17="","—",TODAY()-F17)))),"—") -> — | M17: =IFERROR(IF(A17="","—",IF(OR(H17="Selesai",H17="Cancel"),"✓ Done",IF(G17="","—",G17-TODAY()))),"—") -> —
J18: =IFERROR(IF(OR(A18="",E18=0),0,I18/E18),0) -> 0 | K18: =IFERROR(IF(A18="","—",IF(H18="Selesai","✓ Selesai",IF(H18="Cancel","✗ Cancel",IF(E18=0,"—",IF(J18=0,"✓ BAGUS",IF(J18<=PARAM_REJECT_MAJOR,"⚠ MINOR",IF(J18<=PARAM_REJECT_MAX,"⚠ PERHATIAN","🚨 ESKALASI"))))))), "—") -> — | L18: =IFERROR(IF(A18="","—",IF(H18="Selesai","✓ Selesai",IF(H18="Cancel","✗ Cancel",IF(F18="","—",TODAY()-F18)))),"—") -> — | M18: =IFERROR(IF(A18="","—",IF(OR(H18="Selesai",H18="Cancel"),"✓ Done",IF(G18="","—",G18-TODAY()))),"—") -> —
J19: =IFERROR(IF(OR(A19="",E19=0),0,I19/E19),0) -> 0 | K19: =IFERROR(IF(A19="","—",IF(H19="Selesai","✓ Selesai",IF(H19="Cancel","✗ Cancel",IF(E19=0,"—",IF(J19=0,"✓ BAGUS",IF(J19<=PARAM_REJECT_MAJOR,"⚠ MINOR",IF(J19<=PARAM_REJECT_MAX,"⚠ PERHATIAN","🚨 ESKALASI"))))))), "—") -> — | L19: =IFERROR(IF(A19="","—",IF(H19="Selesai","✓ Selesai",IF(H19="Cancel","✗ Cancel",IF(F19="","—",TODAY()-F19)))),"—") -> — | M19: =IFERROR(IF(A19="","—",IF(OR(H19="Selesai",H19="Cancel"),"✓ Done",IF(G19="","—",G19-TODAY()))),"—") -> —
J20: =IFERROR(IF(OR(A20="",E20=0),0,I20/E20),0) -> 0 | K20: =IFERROR(IF(A20="","—",IF(H20="Selesai","✓ Selesai",IF(H20="Cancel","✗ Cancel",IF(E20=0,"—",IF(J20=0,"✓ BAGUS",IF(J20<=PARAM_REJECT_MAJOR,"⚠ MINOR",IF(J20<=PARAM_REJECT_MAX,"⚠ PERHATIAN","🚨 ESKALASI"))))))), "—") -> — | L20: =IFERROR(IF(A20="","—",IF(H20="Selesai","✓ Selesai",IF(H20="Cancel","✗ Cancel",IF(F20="","—",TODAY()-F20)))),"—") -> — | M20: =IFERROR(IF(A20="","—",IF(OR(H20="Selesai",H20="Cancel"),"✓ Done",IF(G20="","—",G20-TODAY()))),"—") -> —
J21: =IFERROR(IF(OR(A21="",E21=0),0,I21/E21),0) -> 0 | K21: =IFERROR(IF(A21="","—",IF(H21="Selesai","✓ Selesai",IF(H21="Cancel","✗ Cancel",IF(E21=0,"—",IF(J21=0,"✓ BAGUS",IF(J21<=PARAM_REJECT_MAJOR,"⚠ MINOR",IF(J21<=PARAM_REJECT_MAX,"⚠ PERHATIAN","🚨 ESKALASI"))))))), "—") -> — | L21: =IFERROR(IF(A21="","—",IF(H21="Selesai","✓ Selesai",IF(H21="Cancel","✗ Cancel",IF(F21="","—",TODAY()-F21)))),"—") -> — | M21: =IFERROR(IF(A21="","—",IF(OR(H21="Selesai",H21="Cancel"),"✓ Done",IF(G21="","—",G21-TODAY()))),"—") -> —
J22: =IFERROR(IF(OR(A22="",E22=0),0,I22/E22),0) -> 0 | K22: =IFERROR(IF(A22="","—",IF(H22="Selesai","✓ Selesai",IF(H22="Cancel","✗ Cancel",IF(E22=0,"—",IF(J22=0,"✓ BAGUS",IF(J22<=PARAM_REJECT_MAJOR,"⚠ MINOR",IF(J22<=PARAM_REJECT_MAX,"⚠ PERHATIAN","🚨 ESKALASI"))))))), "—") -> — | L22: =IFERROR(IF(A22="","—",IF(H22="Selesai","✓ Selesai",IF(H22="Cancel","✗ Cancel",IF(F22="","—",TODAY()-F22)))),"—") -> — | M22: =IFERROR(IF(A22="","—",IF(OR(H22="Selesai",H22="Cancel"),"✓ Done",IF(G22="","—",G22-TODAY()))),"—") -> —
... J202: =IFERROR(IF(OR(A202="",E202=0),0,I202/E202),0) -> 0 | K202: =IFERROR(IF(A202="","—",IF(H202="Selesai","✓ Selesai",IF(H202="Cancel","✗ Cancel",IF(E202=0,"—",IF(J202=0,"✓ BAGUS",IF(J202<=PARAM_REJECT_MAJOR,"⚠ MINOR",IF(J202<=PARAM_REJECT_MAX,"⚠ PERHATIAN","🚨 ESKALASI"))))))), "—") -> — | L202: =IFERROR(IF(A202="","—",IF(H202="Selesai","✓ Selesai",IF(H202="Cancel","✗ Cancel",IF(F202="","—",TODAY()-F202)))),"—") -> — | M202: =IFERROR(IF(A202="","—",IF(OR(H202="Selesai",H202="Cancel"),"✓ Done",IF(G202="","—",G202-TODAY()))),"—") -> —
J203: =IFERROR(IF(OR(A203="",E203=0),0,I203/E203),0) -> 0 | K203: =IFERROR(IF(A203="","—",IF(H203="Selesai","✓ Selesai",IF(E203=0,"—",IF(J203=0,"✓ BAGUS",IF(J203<=PARAM_REJECT_MAX,"✓ BAGUS",IF(J203<=0.1,"⚠ PERHATIAN","🚨 ESKALASI")))))),"—") -> — | L203: =IFERROR(IF(A203="","—",IF(H203="Selesai","✓ Selesai",IF(F203="","—",TODAY()-F203))),"—") -> — | M203: =IFERROR(IF(A203="","—",IF(H203="Selesai","✓ Selesai",IF(G203="","—",G203-TODAY()))),"—") -> —

Sheet SALES_TRACKER
A1: ◆ SALES TRACKER · Setiap Transaksi Penjualan ◆
A2: BIRU = isi manual (Tanggal, ORDER_ID, PRODUCT_ID, QTY Terjual) · EMAS = formula otomatis · Kapasitas: 1.000 transaksi
A3: TANGGAL | B3: ORDER_ID | C3: PRODUCT_ID | D3: NAMA PRODUK | E3: QTY TERJUAL | F3: HARGA JUAL (Rp) | G3: TOTAL REVENUE (Rp) | H3: HPP/PCS (Rp) | I3: TOTAL HPP (Rp) | J3: GROSS PROFIT (Rp) | K3: MARGIN %
A4: 2026-04-07 | B4: HZN-2604-004 | C4: PRD-004 | D4: {=IFERROR(IF(C4="","",INDEX(PRODUK!$B:$B,MATCH(C4,PRODUK!$A:$A,0))),"")} -> Tunik Casual Linen | E4: 120 | F4: {=IFERROR(IF(C4="",0,INDEX(PRODUK!$F:$F,MATCH(C4,PRODUK!$A:$A,0))),0)} -> 225000 | G4: =IFERROR(IF(OR(B4="",E4=0),0,E4*F4),0) -> 27000000 | H4: {=IFERROR(IF(B4="",0,INDEX(HPP_ENGINE!$J:$J,MATCH(B4,HPP_ENGINE!$A:$A,0))),0)} -> 124150 | I4: =IFERROR(IF(OR(B4="",E4=0),0,E4*H4),0) -> 14898000 | J4: =IFERROR(IF(B4="",0,G4-I4),0) -> 12102000 | K4: =IFERROR(IF(OR(B4="",G4=0),0,J4/G4),0) -> 0.44822222
A5: 2026-04-08 | B5: HZN-2604-001 | C5: PRD-001 | D5: {=IFERROR(IF(C5="","",INDEX(PRODUK!$B:$B,MATCH(C5,PRODUK!$A:$A,0))),"")} -> Abaya Premium Linen | E5: 80 | F5: {=IFERROR(IF(C5="",0,INDEX(PRODUK!$F:$F,MATCH(C5,PRODUK!$A:$A,0))),0)} -> 350000 | G5: =IFERROR(IF(OR(B5="",E5=0),0,E5*F5),0) -> 28000000 | H5: {=IFERROR(IF(B5="",0,INDEX(HPP_ENGINE!$J:$J,MATCH(B5,HPP_ENGINE!$A:$A,0))),0)} -> 194277.03 | I5: =IFERROR(IF(OR(B5="",E5=0),0,E5*H5),0) -> 15542162 | J5: =IFERROR(IF(B5="",0,G5-I5),0) -> 12457838 | K5: =IFERROR(IF(OR(B5="",G5=0),0,J5/G5),0) -> 0.44492278
A6: 2026-04-09 | B6: HZN-2604-001 | C6: PRD-001 | D6: {=IFERROR(IF(C6="","",INDEX(PRODUK!$B:$B,MATCH(C6,PRODUK!$A:$A,0))),"")} -> Abaya Premium Linen | E6: 68 | F6: {=IFERROR(IF(C6="",0,INDEX(PRODUK!$F:$F,MATCH(C6,PRODUK!$A:$A,0))),0)} -> 350000 | G6: =IFERROR(IF(OR(B6="",E6=0),0,E6*F6),0) -> 23800000 | H6: {=IFERROR(IF(B6="",0,INDEX(HPP_ENGINE!$J:$J,MATCH(B6,HPP_ENGINE!$A:$A,0))),0)} -> 194277.03 | I6: =IFERROR(IF(OR(B6="",E6=0),0,E6*H6),0) -> 13210838 | J6: =IFERROR(IF(B6="",0,G6-I6),0) -> 10589162 | K6: =IFERROR(IF(OR(B6="",G6=0),0,J6/G6),0) -> 0.44492278
A7: 2026-04-10 | B7: HZN-2604-006 | C7: PRD-001 | D7: {=IFERROR(IF(C7="","",INDEX(PRODUK!$B:$B,MATCH(C7,PRODUK!$A:$A,0))),"")} -> Abaya Premium Linen | E7: 100 | F7: {=IFERROR(IF(C7="",0,INDEX(PRODUK!$F:$F,MATCH(C7,PRODUK!$A:$A,0))),0)} -> 350000 | G7: =IFERROR(IF(OR(B7="",E7=0),0,E7*F7),0) -> 35000000 | H7: {=IFERROR(IF(B7="",0,INDEX(HPP_ENGINE!$J:$J,MATCH(B7,HPP_ENGINE!$A:$A,0))),0)} -> 198812.5 | I7: =IFERROR(IF(OR(B7="",E7=0),0,E7*H7),0) -> 19881250 | J7: =IFERROR(IF(B7="",0,G7-I7),0) -> 15118750 | K7: =IFERROR(IF(OR(B7="",G7=0),0,J7/G7),0) -> 0.43196429
D8: {=IFERROR(IF(C8="","",INDEX(PRODUK!$B:$B,MATCH(C8,PRODUK!$A:$A,0))),"")} | F8: {=IFERROR(IF(C8="",0,INDEX(PRODUK!$F:$F,MATCH(C8,PRODUK!$A:$A,0))),0)} -> 0 | G8: =IFERROR(IF(OR(B8="",E8=0),0,E8*F8),0) -> 0 | H8: {=IFERROR(IF(B8="",0,INDEX(HPP_ENGINE!$J:$J,MATCH(B8,HPP_ENGINE!$A:$A,0))),0)} -> 0 | I8: =IFERROR(IF(OR(B8="",E8=0),0,E8*H8),0) -> 0 | J8: =IFERROR(IF(B8="",0,G8-I8),0) -> 0 | K8: =IFERROR(IF(OR(B8="",G8=0),0,J8/G8),0) -> 0
D9: {=IFERROR(IF(C9="","",INDEX(PRODUK!$B:$B,MATCH(C9,PRODUK!$A:$A,0))),"")} | F9: {=IFERROR(IF(C9="",0,INDEX(PRODUK!$F:$F,MATCH(C9,PRODUK!$A:$A,0))),0)} -> 0 | G9: =IFERROR(IF(OR(B9="",E9=0),0,E9*F9),0) -> 0 | H9: {=IFERROR(IF(B9="",0,INDEX(HPP_ENGINE!$J:$J,MATCH(B9,HPP_ENGINE!$A:$A,0))),0)} -> 0 | I9: =IFERROR(IF(OR(B9="",E9=0),0,E9*H9),0) -> 0 | J9: =IFERROR(IF(B9="",0,G9-I9),0) -> 0 | K9: =IFERROR(IF(OR(B9="",G9=0),0,J9/G9),0) -> 0
D10: {=IFERROR(IF(C10="","",INDEX(PRODUK!$B:$B,MATCH(C10,PRODUK!$A:$A,0))),"")} | F10: {=IFERROR(IF(C10="",0,INDEX(PRODUK!$F:$F,MATCH(C10,PRODUK!$A:$A,0))),0)} -> 0 | G10: =IFERROR(IF(OR(B10="",E10=0),0,E10*F10),0) -> 0 | H10: {=IFERROR(IF(B10="",0,INDEX(HPP_ENGINE!$J:$J,MATCH(B10,HPP_ENGINE!$A:$A,0))),0)} -> 0 | I10: =IFERROR(IF(OR(B10="",E10=0),0,E10*H10),0) -> 0 | J10: =IFERROR(IF(B10="",0,G10-I10),0) -> 0 | K10: =IFERROR(IF(OR(B10="",G10=0),0,J10/G10),0) -> 0
D11: {=IFERROR(IF(C11="","",INDEX(PRODUK!$B:$B,MATCH(C11,PRODUK!$A:$A,0))),"")} | F11: {=IFERROR(IF(C11="",0,INDEX(PRODUK!$F:$F,MATCH(C11,PRODUK!$A:$A,0))),0)} -> 0 | G11: =IFERROR(IF(OR(B11="",E11=0),0,E11*F11),0) -> 0 | H11: {=IFERROR(IF(B11="",0,INDEX(HPP_ENGINE!$J:$J,MATCH(B11,HPP_ENGINE!$A:$A,0))),0)} -> 0 | I11: =IFERROR(IF(OR(B11="",E11=0),0,E11*H11),0) -> 0 | J11: =IFERROR(IF(B11="",0,G11-I11),0) -> 0 | K11: =IFERROR(IF(OR(B11="",G11=0),0,J11/G11),0) -> 0
D12: {=IFERROR(IF(C12="","",INDEX(PRODUK!$B:$B,MATCH(C12,PRODUK!$A:$A,0))),"")} | F12: {=IFERROR(IF(C12="",0,INDEX(PRODUK!$F:$F,MATCH(C12,PRODUK!$A:$A,0))),0)} -> 0 | G12: =IFERROR(IF(OR(B12="",E12=0),0,E12*F12),0) -> 0 | H12: {=IFERROR(IF(B12="",0,INDEX(HPP_ENGINE!$J:$J,MATCH(B12,HPP_ENGINE!$A:$A,0))),0)} -> 0 | I12: =IFERROR(IF(OR(B12="",E12=0),0,E12*H12),0) -> 0 | J12: =IFERROR(IF(B12="",0,G12-I12),0) -> 0 | K12: =IFERROR(IF(OR(B12="",G12=0),0,J12/G12),0) -> 0
D13: {=IFERROR(IF(C13="","",INDEX(PRODUK!$B:$B,MATCH(C13,PRODUK!$A:$A,0))),"")} | F13: {=IFERROR(IF(C13="",0,INDEX(PRODUK!$F:$F,MATCH(C13,PRODUK!$A:$A,0))),0)} -> 0 | G13: =IFERROR(IF(OR(B13="",E13=0),0,E13*F13),0) -> 0 | H13: {=IFERROR(IF(B13="",0,INDEX(HPP_ENGINE!$J:$J,MATCH(B13,HPP_ENGINE!$A:$A,0))),0)} -> 0 | I13: =IFERROR(IF(OR(B13="",E13=0),0,E13*H13),0) -> 0 | J13: =IFERROR(IF(B13="",0,G13-I13),0) -> 0 | K13: =IFERROR(IF(OR(B13="",G13=0),0,J13/G13),0) -> 0
D14: {=IFERROR(IF(C14="","",INDEX(PRODUK!$B:$B,MATCH(C14,PRODUK!$A:$A,0))),"")} | F14: {=IFERROR(IF(C14="",0,INDEX(PRODUK!$F:$F,MATCH(C14,PRODUK!$A:$A,0))),0)} -> 0 | G14: =IFERROR(IF(OR(B14="",E14=0),0,E14*F14),0) -> 0 | H14: {=IFERROR(IF(B14="",0,INDEX(HPP_ENGINE!$J:$J,MATCH(B14,HPP_ENGINE!$A:$A,0))),0)} -> 0 | I14: =IFERROR(IF(OR(B14="",E14=0),0,E14*H14),0) -> 0 | J14: =IFERROR(IF(B14="",0,G14-I14),0) -> 0 | K14: =IFERROR(IF(OR(B14="",G14=0),0,J14/G14),0) -> 0
D15: {=IFERROR(IF(C15="","",INDEX(PRODUK!$B:$B,MATCH(C15,PRODUK!$A:$A,0))),"")} | F15: {=IFERROR(IF(C15="",0,INDEX(PRODUK!$F:$F,MATCH(C15,PRODUK!$A:$A,0))),0)} -> 0 | G15: =IFERROR(IF(OR(B15="",E15=0),0,E15*F15),0) -> 0 | H15: {=IFERROR(IF(B15="",0,INDEX(HPP_ENGINE!$J:$J,MATCH(B15,HPP_ENGINE!$A:$A,0))),0)} -> 0 | I15: =IFERROR(IF(OR(B15="",E15=0),0,E15*H15),0) -> 0 | J15: =IFERROR(IF(B15="",0,G15-I15),0) -> 0 | K15: =IFERROR(IF(OR(B15="",G15=0),0,J15/G15),0) -> 0
D16: {=IFERROR(IF(C16="","",INDEX(PRODUK!$B:$B,MATCH(C16,PRODUK!$A:$A,0))),"")} | F16: {=IFERROR(IF(C16="",0,INDEX(PRODUK!$F:$F,MATCH(C16,PRODUK!$A:$A,0))),0)} -> 0 | G16: =IFERROR(IF(OR(B16="",E16=0),0,E16*F16),0) -> 0 | H16: {=IFERROR(IF(B16="",0,INDEX(HPP_ENGINE!$J:$J,MATCH(B16,HPP_ENGINE!$A:$A,0))),0)} -> 0 | I16: =IFERROR(IF(OR(B16="",E16=0),0,E16*H16),0) -> 0 | J16: =IFERROR(IF(B16="",0,G16-I16),0) -> 0 | K16: =IFERROR(IF(OR(B16="",G16=0),0,J16/G16),0) -> 0
D17: {=IFERROR(IF(C17="","",INDEX(PRODUK!$B:$B,MATCH(C17,PRODUK!$A:$A,0))),"")} | F17: {=IFERROR(IF(C17="",0,INDEX(PRODUK!$F:$F,MATCH(C17,PRODUK!$A:$A,0))),0)} -> 0 | G17: =IFERROR(IF(OR(B17="",E17=0),0,E17*F17),0) -> 0 | H17: {=IFERROR(IF(B17="",0,INDEX(HPP_ENGINE!$J:$J,MATCH(B17,HPP_ENGINE!$A:$A,0))),0)} -> 0 | I17: =IFERROR(IF(OR(B17="",E17=0),0,E17*H17),0) -> 0 | J17: =IFERROR(IF(B17="",0,G17-I17),0) -> 0 | K17: =IFERROR(IF(OR(B17="",G17=0),0,J17/G17),0) -> 0
D18: {=IFERROR(IF(C18="","",INDEX(PRODUK!$B:$B,MATCH(C18,PRODUK!$A:$A,0))),"")} | F18: {=IFERROR(IF(C18="",0,INDEX(PRODUK!$F:$F,MATCH(C18,PRODUK!$A:$A,0))),0)} -> 0 | G18: =IFERROR(IF(OR(B18="",E18=0),0,E18*F18),0) -> 0 | H18: {=IFERROR(IF(B18="",0,INDEX(HPP_ENGINE!$J:$J,MATCH(B18,HPP_ENGINE!$A:$A,0))),0)} -> 0 | I18: =IFERROR(IF(OR(B18="",E18=0),0,E18*H18),0) -> 0 | J18: =IFERROR(IF(B18="",0,G18-I18),0) -> 0 | K18: =IFERROR(IF(OR(B18="",G18=0),0,J18/G18),0) -> 0
D19: {=IFERROR(IF(C19="","",INDEX(PRODUK!$B:$B,MATCH(C19,PRODUK!$A:$A,0))),"")} | F19: {=IFERROR(IF(C19="",0,INDEX(PRODUK!$F:$F,MATCH(C19,PRODUK!$A:$A,0))),0)} -> 0 | G19: =IFERROR(IF(OR(B19="",E19=0),0,E19*F19),0) -> 0 | H19: {=IFERROR(IF(B19="",0,INDEX(HPP_ENGINE!$J:$J,MATCH(B19,HPP_ENGINE!$A:$A,0))),0)} -> 0 | I19: =IFERROR(IF(OR(B19="",E19=0),0,E19*H19),0) -> 0 | J19: =IFERROR(IF(B19="",0,G19-I19),0) -> 0 | K19: =IFERROR(IF(OR(B19="",G19=0),0,J19/G19),0) -> 0
... D1002: {=IFERROR(IF(C1002="","",INDEX(PRODUK!$B:$B,MATCH(C1002,PRODUK!$A:$A,0))),"")} | F1002: {=IFERROR(IF(C1002="",0,INDEX(PRODUK!$F:$F,MATCH(C1002,PRODUK!$A:$A,0))),0)} -> 0 | G1002: =IFERROR(IF(OR(B1002="",E1002=0),0,E1002*F1002),0) -> 0 | H1002: {=IFERROR(IF(B1002="",0,INDEX(HPP_ENGINE!$J:$J,MATCH(B1002,HPP_ENGINE!$A:$A,0))),0)} -> 0 | I1002: =IFERROR(IF(OR(B1002="",E1002=0),0,E1002*H1002),0) -> 0 | J1002: =IFERROR(IF(B1002="",0,G1002-I1002),0) -> 0 | K1002: =IFERROR(IF(OR(B1002="",G1002=0),0,J1002/G1002),0) -> 0
D1003: =IFERROR(IF(C1003="","",VLOOKUP(C1003,PRODUK!A:B,2,0)),"") | F1003: =IFERROR(IF(C1003="",0,VLOOKUP(C1003,PRODUK!A:F,6,0)),0) -> 0 | G1003: =IFERROR(IF(OR(B1003="",E1003=0),0,E1003*F1003),0) -> 0 | H1003: =IFERROR(IF(B1003="",0,VLOOKUP(B1003,HPP_ENGINE!A:J,10,0)),0) -> 0 | I1003: =IFERROR(IF(OR(B1003="",E1003=0),0,E1003*H1003),0) -> 0 | J1003: =IFERROR(IF(B1003="",0,G1003-I1003),0) -> 0 | K1003: =IFERROR(IF(OR(B1003="",G1003=0),0,J1003/G1003),0) -> 0

Sheet SUMMARY_ENGINE
A1: ◆ SUMMARY ENGINE · Agregasi Keuangan Per Order ◆
A2: Cukup isi ORDER_ID di kolom A → seluruh data otomatis teraggregasi dari HPP_ENGINE, SALES_TRACKER, PRODUCTION_PLAN
A3: ORDER_ID | B3: PRODUCT_ID | C3: NAMA PRODUK | D3: QTY PLAN | E3: QTY PRODUKSI | F3: QTY TERJUAL | G3: SISA STOK | H3: TOTAL COST (Rp) | I3: TOTAL REVENUE (Rp) | J3: GROSS PROFIT (Rp) | K3: MARGIN % | L3: ROI % | M3: SELL THRU % | N3: STATUS ORDER
A4: HZN-2604-001 | B4: {=IFERROR(IF(A4="","",INDEX(HPP_ENGINE!$B:$B,MATCH(A4,HPP_ENGINE!$A:$A,0))),"")} -> PRD-001 | C4: {=IFERROR(IF(A4="","",INDEX(HPP_ENGINE!$C:$C,MATCH(A4,HPP_ENGINE!$A:$A,0))),"")} -> Abaya Premium Linen | D4: {=IFERROR(IF(A4="",0,INDEX(PRODUCTION_PLAN!$D:$D,MATCH(A4,PRODUCTION_PLAN!$A:$A,0))),0)} -> 150 | E4: {=IFERROR(IF(A4="",0,INDEX(HPP_ENGINE!$D:$D,MATCH(A4,HPP_ENGINE!$A:$A,0))),0)} -> 148 | F4: =IFERROR(IF(A4="",0,SUMIFS(SALES_TRACKER!$E$4:$E$1003,SALES_TRACKER!$B$4:$B$1003,A4)),0) -> 148 | G4: =IFERROR(IF(A4="",0,E4-F4),0) -> 0 | H4: {=IFERROR(IF(A4="",0,INDEX(HPP_ENGINE!$I:$I,MATCH(A4,HPP_ENGINE!$A:$A,0))),0)} -> 28753000 | I4: =IFERROR(IF(A4="",0,SUMIFS(SALES_TRACKER!$G$4:$G$1003,SALES_TRACKER!$B$4:$B$1003,A4)),0) -> 51800000 | J4: =IFERROR(IF(A4="",0,I4-H4),0) -> 23047000 | K4: =IFERROR(IF(A4="",0,IF(I4=0,IF(H4>0,-1,0),J4/I4)),0) -> 0.44492278 | L4: =IFERROR(IF(OR(A4="",H4=0),0,J4/H4),0) -> 0.80155114 | M4: =IFERROR(IF(OR(A4="",E4=0),0,F4/E4),0) -> 1 | N4: =IFERROR(IF(A4="","—",IF(COUNTIF(HPP_ENGINE!$A$4:$A$203,A4)=0,"⚠ BELUM DI HPP",IF(E4=0,"PLANNING",IF(M4>=1,"SOLD OUT",IF(M4>=0.7,"ON TRACK",IF(M4>=0.3,"SLOW MOVE",IF(M4>0,"STUCK","BELUM TERJUAL"))))))),"—") -> SOLD OUT
A5: HZN-2604-002 | B5: {=IFERROR(IF(A5="","",INDEX(HPP_ENGINE!$B:$B,MATCH(A5,HPP_ENGINE!$A:$A,0))),"")} -> PRD-002 | C5: {=IFERROR(IF(A5="","",INDEX(HPP_ENGINE!$C:$C,MATCH(A5,HPP_ENGINE!$A:$A,0))),"")} -> Gamis Velvet Bordir | D5: {=IFERROR(IF(A5="",0,INDEX(PRODUCTION_PLAN!$D:$D,MATCH(A5,PRODUCTION_PLAN!$A:$A,0))),0)} -> 200 | E5: {=IFERROR(IF(A5="",0,INDEX(HPP_ENGINE!$D:$D,MATCH(A5,HPP_ENGINE!$A:$A,0))),0)} -> 185 | F5: =IFERROR(IF(A5="",0,SUMIFS(SALES_TRACKER!$E$4:$E$1003,SALES_TRACKER!$B$4:$B$1003,A5)),0) -> 0 | G5: =IFERROR(IF(A5="",0,E5-F5),0) -> 185 | H5: {=IFERROR(IF(A5="",0,INDEX(HPP_ENGINE!$I:$I,MATCH(A5,HPP_ENGINE!$A:$A,0))),0)} -> 45628000 | I5: =IFERROR(IF(A5="",0,SUMIFS(SALES_TRACKER!$G$4:$G$1003,SALES_TRACKER!$B$4:$B$1003,A5)),0) -> 0 | J5: =IFERROR(IF(A5="",0,I5-H5),0) -> -45628000 | K5: =IFERROR(IF(A5="",0,IF(I5=0,IF(H5>0,-1,0),J5/I5)),0) -> -1 | L5: =IFERROR(IF(OR(A5="",H5=0),0,J5/H5),0) -> -1 | M5: =IFERROR(IF(OR(A5="",E5=0),0,F5/E5),0) -> 0 | N5: =IFERROR(IF(A5="","—",IF(COUNTIF(HPP_ENGINE!$A$4:$A$203,A5)=0,"⚠ BELUM DI HPP",IF(E5=0,"PLANNING",IF(M5>=1,"SOLD OUT",IF(M5>=0.7,"ON TRACK",IF(M5>=0.3,"SLOW MOVE",IF(M5>0,"STUCK","BELUM TERJUAL"))))))),"—") -> BELUM TERJUAL
A6: HZN-2604-003 | B6: {=IFERROR(IF(A6="","",INDEX(HPP_ENGINE!$B:$B,MATCH(A6,HPP_ENGINE!$A:$A,0))),"")} -> PRD-003 | C6: {=IFERROR(IF(A6="","",INDEX(HPP_ENGINE!$C:$C,MATCH(A6,HPP_ENGINE!$A:$A,0))),"")} -> Kaftan Silk Premium | D6: {=IFERROR(IF(A6="",0,INDEX(PRODUCTION_PLAN!$D:$D,MATCH(A6,PRODUCTION_PLAN!$A:$A,0))),0)} -> 80 | E6: {=IFERROR(IF(A6="",0,INDEX(HPP_ENGINE!$D:$D,MATCH(A6,HPP_ENGINE!$A:$A,0))),0)} -> 80 | F6: =IFERROR(IF(A6="",0,SUMIFS(SALES_TRACKER!$E$4:$E$1003,SALES_TRACKER!$B$4:$B$1003,A6)),0) -> 0 | G6: =IFERROR(IF(A6="",0,E6-F6),0) -> 80 | H6: {=IFERROR(IF(A6="",0,INDEX(HPP_ENGINE!$I:$I,MATCH(A6,HPP_ENGINE!$A:$A,0))),0)} -> 22152000 | I6: =IFERROR(IF(A6="",0,SUMIFS(SALES_TRACKER!$G$4:$G$1003,SALES_TRACKER!$B$4:$B$1003,A6)),0) -> 0 | J6: =IFERROR(IF(A6="",0,I6-H6),0) -> -22152000 | K6: =IFERROR(IF(A6="",0,IF(I6=0,IF(H6>0,-1,0),J6/I6)),0) -> -1 | L6: =IFERROR(IF(OR(A6="",H6=0),0,J6/H6),0) -> -1 | M6: =IFERROR(IF(OR(A6="",E6=0),0,F6/E6),0) -> 0 | N6: =IFERROR(IF(A6="","—",IF(COUNTIF(HPP_ENGINE!$A$4:$A$203,A6)=0,"⚠ BELUM DI HPP",IF(E6=0,"PLANNING",IF(M6>=1,"SOLD OUT",IF(M6>=0.7,"ON TRACK",IF(M6>=0.3,"SLOW MOVE",IF(M6>0,"STUCK","BELUM TERJUAL"))))))),"—") -> BELUM TERJUAL
A7: HZN-2604-004 | B7: {=IFERROR(IF(A7="","",INDEX(HPP_ENGINE!$B:$B,MATCH(A7,HPP_ENGINE!$A:$A,0))),"")} -> PRD-004 | C7: {=IFERROR(IF(A7="","",INDEX(HPP_ENGINE!$C:$C,MATCH(A7,HPP_ENGINE!$A:$A,0))),"")} -> Tunik Casual Linen | D7: {=IFERROR(IF(A7="",0,INDEX(PRODUCTION_PLAN!$D:$D,MATCH(A7,PRODUCTION_PLAN!$A:$A,0))),0)} -> 120 | E7: {=IFERROR(IF(A7="",0,INDEX(HPP_ENGINE!$D:$D,MATCH(A7,HPP_ENGINE!$A:$A,0))),0)} -> 120 | F7: =IFERROR(IF(A7="",0,SUMIFS(SALES_TRACKER!$E$4:$E$1003,SALES_TRACKER!$B$4:$B$1003,A7)),0) -> 120 | G7: =IFERROR(IF(A7="",0,E7-F7),0) -> 0 | H7: {=IFERROR(IF(A7="",0,INDEX(HPP_ENGINE!$I:$I,MATCH(A7,HPP_ENGINE!$A:$A,0))),0)} -> 14898000 | I7: =IFERROR(IF(A7="",0,SUMIFS(SALES_TRACKER!$G$4:$G$1003,SALES_TRACKER!$B$4:$B$1003,A7)),0) -> 27000000 | J7: =IFERROR(IF(A7="",0,I7-H7),0) -> 12102000 | K7: =IFERROR(IF(A7="",0,IF(I7=0,IF(H7>0,-1,0),J7/I7)),0) -> 0.44822222 | L7: =IFERROR(IF(OR(A7="",H7=0),0,J7/H7),0) -> 0.8123238 | M7: =IFERROR(IF(OR(A7="",E7=0),0,F7/E7),0) -> 1 | N7: =IFERROR(IF(A7="","—",IF(COUNTIF(HPP_ENGINE!$A$4:$A$203,A7)=0,"⚠ BELUM DI HPP",IF(E7=0,"PLANNING",IF(M7>=1,"SOLD OUT",IF(M7>=0.7,"ON TRACK",IF(M7>=0.3,"SLOW MOVE",IF(M7>0,"STUCK","BELUM TERJUAL"))))))),"—") -> SOLD OUT
A8: HZN-2604-005 | B8: {=IFERROR(IF(A8="","",INDEX(HPP_ENGINE!$B:$B,MATCH(A8,HPP_ENGINE!$A:$A,0))),"")} -> PRD-005 | C8: {=IFERROR(IF(A8="","",INDEX(HPP_ENGINE!$C:$C,MATCH(A8,HPP_ENGINE!$A:$A,0))),"")} -> Dress Batik Modern | D8: {=IFERROR(IF(A8="",0,INDEX(PRODUCTION_PLAN!$D:$D,MATCH(A8,PRODUCTION_PLAN!$A:$A,0))),0)} -> 100 | E8: {=IFERROR(IF(A8="",0,INDEX(HPP_ENGINE!$D:$D,MATCH(A8,HPP_ENGINE!$A:$A,0))),0)} -> 50 | F8: =IFERROR(IF(A8="",0,SUMIFS(SALES_TRACKER!$E$4:$E$1003,SALES_TRACKER!$B$4:$B$1003,A8)),0) -> 0 | G8: =IFERROR(IF(A8="",0,E8-F8),0) -> 50 | H8: {=IFERROR(IF(A8="",0,INDEX(HPP_ENGINE!$I:$I,MATCH(A8,HPP_ENGINE!$A:$A,0))),0)} -> 15800000 | I8: =IFERROR(IF(A8="",0,SUMIFS(SALES_TRACKER!$G$4:$G$1003,SALES_TRACKER!$B$4:$B$1003,A8)),0) -> 0 | J8: =IFERROR(IF(A8="",0,I8-H8),0) -> -15800000 | K8: =IFERROR(IF(A8="",0,IF(I8=0,IF(H8>0,-1,0),J8/I8)),0) -> -1 | L8: =IFERROR(IF(OR(A8="",H8=0),0,J8/H8),0) -> -1 | M8: =IFERROR(IF(OR(A8="",E8=0),0,F8/E8),0) -> 0 | N8: =IFERROR(IF(A8="","—",IF(COUNTIF(HPP_ENGINE!$A$4:$A$203,A8)=0,"⚠ BELUM DI HPP",IF(E8=0,"PLANNING",IF(M8>=1,"SOLD OUT",IF(M8>=0.7,"ON TRACK",IF(M8>=0.3,"SLOW MOVE",IF(M8>0,"STUCK","BELUM TERJUAL"))))))),"—") -> BELUM TERJUAL
A9: HZN-2604-006 | B9: {=IFERROR(IF(A9="","",INDEX(HPP_ENGINE!$B:$B,MATCH(A9,HPP_ENGINE!$A:$A,0))),"")} -> PRD-001 | C9: {=IFERROR(IF(A9="","",INDEX(HPP_ENGINE!$C:$C,MATCH(A9,HPP_ENGINE!$A:$A,0))),"")} -> Abaya Premium Linen | D9: {=IFERROR(IF(A9="",0,INDEX(PRODUCTION_PLAN!$D:$D,MATCH(A9,PRODUCTION_PLAN!$A:$A,0))),0)} -> 250 | E9: {=IFERROR(IF(A9="",0,INDEX(HPP_ENGINE!$D:$D,MATCH(A9,HPP_ENGINE!$A:$A,0))),0)} -> 240 | F9: =IFERROR(IF(A9="",0,SUMIFS(SALES_TRACKER!$E$4:$E$1003,SALES_TRACKER!$B$4:$B$1003,A9)),0) -> 100 | G9: =IFERROR(IF(A9="",0,E9-F9),0) -> 140 | H9: {=IFERROR(IF(A9="",0,INDEX(HPP_ENGINE!$I:$I,MATCH(A9,HPP_ENGINE!$A:$A,0))),0)} -> 47715000 | I9: =IFERROR(IF(A9="",0,SUMIFS(SALES_TRACKER!$G$4:$G$1003,SALES_TRACKER!$B$4:$B$1003,A9)),0) -> 35000000 | J9: =IFERROR(IF(A9="",0,I9-H9),0) -> -12715000 | K9: =IFERROR(IF(A9="",0,IF(I9=0,IF(H9>0,-1,0),J9/I9)),0) -> -0.36328571 | L9: =IFERROR(IF(OR(A9="",H9=0),0,J9/H9),0) -> -0.26647805 | M9: =IFERROR(IF(OR(A9="",E9=0),0,F9/E9),0) -> 0.41666667 | N9: =IFERROR(IF(A9="","—",IF(COUNTIF(HPP_ENGINE!$A$4:$A$203,A9)=0,"⚠ BELUM DI HPP",IF(E9=0,"PLANNING",IF(M9>=1,"SOLD OUT",IF(M9>=0.7,"ON TRACK",IF(M9>=0.3,"SLOW MOVE",IF(M9>0,"STUCK","BELUM TERJUAL"))))))),"—") -> SLOW MOVE
A10: HZN-2604-007 | B10: {=IFERROR(IF(A10="","",INDEX(HPP_ENGINE!$B:$B,MATCH(A10,HPP_ENGINE!$A:$A,0))),"")} -> PRD-002 | C10: {=IFERROR(IF(A10="","",INDEX(HPP_ENGINE!$C:$C,MATCH(A10,HPP_ENGINE!$A:$A,0))),"")} -> Gamis Velvet Bordir | D10: {=IFERROR(IF(A10="",0,INDEX(PRODUCTION_PLAN!$D:$D,MATCH(A10,PRODUCTION_PLAN!$A:$A,0))),0)} -> 180 | E10: {=IFERROR(IF(A10="",0,INDEX(HPP_ENGINE!$D:$D,MATCH(A10,HPP_ENGINE!$A:$A,0))),0)} -> 170 | F10: =IFERROR(IF(A10="",0,SUMIFS(SALES_TRACKER!$E$4:$E$1003,SALES_TRACKER!$B$4:$B$1003,A10)),0) -> 0 | G10: =IFERROR(IF(A10="",0,E10-F10),0) -> 170 | H10: {=IFERROR(IF(A10="",0,INDEX(HPP_ENGINE!$I:$I,MATCH(A10,HPP_ENGINE!$A:$A,0))),0)} -> 41021000 | I10: =IFERROR(IF(A10="",0,SUMIFS(SALES_TRACKER!$G$4:$G$1003,SALES_TRACKER!$B$4:$B$1003,A10)),0) -> 0 | J10: =IFERROR(IF(A10="",0,I10-H10),0) -> -41021000 | K10: =IFERROR(IF(A10="",0,IF(I10=0,IF(H10>0,-1,0),J10/I10)),0) -> -1 | L10: =IFERROR(IF(OR(A10="",H10=0),0,J10/H10),0) -> -1 | M10: =IFERROR(IF(OR(A10="",E10=0),0,F10/E10),0) -> 0 | N10: =IFERROR(IF(A10="","—",IF(COUNTIF(HPP_ENGINE!$A$4:$A$203,A10)=0,"⚠ BELUM DI HPP",IF(E10=0,"PLANNING",IF(M10>=1,"SOLD OUT",IF(M10>=0.7,"ON TRACK",IF(M10>=0.3,"SLOW MOVE",IF(M10>0,"STUCK","BELUM TERJUAL"))))))),"—") -> BELUM TERJUAL
B11: {=IFERROR(IF(A11="","",INDEX(HPP_ENGINE!$B:$B,MATCH(A11,HPP_ENGINE!$A:$A,0))),"")} | C11: {=IFERROR(IF(A11="","",INDEX(HPP_ENGINE!$C:$C,MATCH(A11,HPP_ENGINE!$A:$A,0))),"")} | D11: {=IFERROR(IF(A11="",0,INDEX(PRODUCTION_PLAN!$D:$D,MATCH(A11,PRODUCTION_PLAN!$A:$A,0))),0)} -> 0 | E11: {=IFERROR(IF(A11="",0,INDEX(HPP_ENGINE!$D:$D,MATCH(A11,HPP_ENGINE!$A:$A,0))),0)} -> 0 | F11: =IFERROR(IF(A11="",0,SUMIFS(SALES_TRACKER!$E$4:$E$1003,SALES_TRACKER!$B$4:$B$1003,A11)),0) -> 0 | G11: =IFERROR(IF(A11="",0,E11-F11),0) -> 0 | H11: {=IFERROR(IF(A11="",0,INDEX(HPP_ENGINE!$I:$I,MATCH(A11,HPP_ENGINE!$A:$A,0))),0)} -> 0 | I11: =IFERROR(IF(A11="",0,SUMIFS(SALES_TRACKER!$G$4:$G$1003,SALES_TRACKER!$B$4:$B$1003,A11)),0) -> 0 | J11: =IFERROR(IF(A11="",0,I11-H11),0) -> 0 | K11: =IFERROR(IF(A11="",0,IF(I11=0,IF(H11>0,-1,0),J11/I11)),0) -> 0 | L11: =IFERROR(IF(OR(A11="",H11=0),0,J11/H11),0) -> 0 | M11: =IFERROR(IF(OR(A11="",E11=0),0,F11/E11),0) -> 0 | N11: =IFERROR(IF(A11="","—",IF(COUNTIF(HPP_ENGINE!$A$4:$A$203,A11)=0,"⚠ BELUM DI HPP",IF(E11=0,"PLANNING",IF(M11>=1,"SOLD OUT",IF(M11>=0.7,"ON TRACK",IF(M11>=0.3,"SLOW MOVE",IF(M11>0,"STUCK","BELUM TERJUAL"))))))),"—") -> —
B12: {=IFERROR(IF(A12="","",INDEX(HPP_ENGINE!$B:$B,MATCH(A12,HPP_ENGINE!$A:$A,0))),"")} | C12: {=IFERROR(IF(A12="","",INDEX(HPP_ENGINE!$C:$C,MATCH(A12,HPP_ENGINE!$A:$A,0))),"")} | D12: {=IFERROR(IF(A12="",0,INDEX(PRODUCTION_PLAN!$D:$D,MATCH(A12,PRODUCTION_PLAN!$A:$A,0))),0)} -> 0 | E12: {=IFERROR(IF(A12="",0,INDEX(HPP_ENGINE!$D:$D,MATCH(A12,HPP_ENGINE!$A:$A,0))),0)} -> 0 | F12: =IFERROR(IF(A12="",0,SUMIFS(SALES_TRACKER!$E$4:$E$1003,SALES_TRACKER!$B$4:$B$1003,A12)),0) -> 0 | G12: =IFERROR(IF(A12="",0,E12-F12),0) -> 0 | H12: {=IFERROR(IF(A12="",0,INDEX(HPP_ENGINE!$I:$I,MATCH(A12,HPP_ENGINE!$A:$A,0))),0)} -> 0 | I12: =IFERROR(IF(A12="",0,SUMIFS(SALES_TRACKER!$G$4:$G$1003,SALES_TRACKER!$B$4:$B$1003,A12)),0) -> 0 | J12: =IFERROR(IF(A12="",0,I12-H12),0) -> 0 | K12: =IFERROR(IF(A12="",0,IF(I12=0,IF(H12>0,-1,0),J12/I12)),0) -> 0 | L12: =IFERROR(IF(OR(A12="",H12=0),0,J12/H12),0) -> 0 | M12: =IFERROR(IF(OR(A12="",E12=0),0,F12/E12),0) -> 0 | N12: =IFERROR(IF(A12="","—",IF(COUNTIF(HPP_ENGINE!$A$4:$A$203,A12)=0,"⚠ BELUM DI HPP",IF(E12=0,"PLANNING",IF(M12>=1,"SOLD OUT",IF(M12>=0.7,"ON TRACK",IF(M12>=0.3,"SLOW MOVE",IF(M12>0,"STUCK","BELUM TERJUAL"))))))),"—") -> —
B13: {=IFERROR(IF(A13="","",INDEX(HPP_ENGINE!$B:$B,MATCH(A13,HPP_ENGINE!$A:$A,0))),"")} | C13: {=IFERROR(IF(A13="","",INDEX(HPP_ENGINE!$C:$C,MATCH(A13,HPP_ENGINE!$A:$A,0))),"")} | D13: {=IFERROR(IF(A13="",0,INDEX(PRODUCTION_PLAN!$D:$D,MATCH(A13,PRODUCTION_PLAN!$A:$A,0))),0)} -> 0 | E13: {=IFERROR(IF(A13="",0,INDEX(HPP_ENGINE!$D:$D,MATCH(A13,HPP_ENGINE!$A:$A,0))),0)} -> 0 | F13: =IFERROR(IF(A13="",0,SUMIFS(SALES_TRACKER!$E$4:$E$1003,SALES_TRACKER!$B$4:$B$1003,A13)),0) -> 0 | G13: =IFERROR(IF(A13="",0,E13-F13),0) -> 0 | H13: {=IFERROR(IF(A13="",0,INDEX(HPP_ENGINE!$I:$I,MATCH(A13,HPP_ENGINE!$A:$A,0))),0)} -> 0 | I13: =IFERROR(IF(A13="",0,SUMIFS(SALES_TRACKER!$G$4:$G$1003,SALES_TRACKER!$B$4:$B$1003,A13)),0) -> 0 | J13: =IFERROR(IF(A13="",0,I13-H13),0) -> 0 | K13: =IFERROR(IF(A13="",0,IF(I13=0,IF(H13>0,-1,0),J13/I13)),0) -> 0 | L13: =IFERROR(IF(OR(A13="",H13=0),0,J13/H13),0) -> 0 | M13: =IFERROR(IF(OR(A13="",E13=0),0,F13/E13),0) -> 0 | N13: =IFERROR(IF(A13="","—",IF(COUNTIF(HPP_ENGINE!$A$4:$A$203,A13)=0,"⚠ BELUM DI HPP",IF(E13=0,"PLANNING",IF(M13>=1,"SOLD OUT",IF(M13>=0.7,"ON TRACK",IF(M13>=0.3,"SLOW MOVE",IF(M13>0,"STUCK","BELUM TERJUAL"))))))),"—") -> —
B14: {=IFERROR(IF(A14="","",INDEX(HPP_ENGINE!$B:$B,MATCH(A14,HPP_ENGINE!$A:$A,0))),"")} | C14: {=IFERROR(IF(A14="","",INDEX(HPP_ENGINE!$C:$C,MATCH(A14,HPP_ENGINE!$A:$A,0))),"")} | D14: {=IFERROR(IF(A14="",0,INDEX(PRODUCTION_PLAN!$D:$D,MATCH(A14,PRODUCTION_PLAN!$A:$A,0))),0)} -> 0 | E14: {=IFERROR(IF(A14="",0,INDEX(HPP_ENGINE!$D:$D,MATCH(A14,HPP_ENGINE!$A:$A,0))),0)} -> 0 | F14: =IFERROR(IF(A14="",0,SUMIFS(SALES_TRACKER!$E$4:$E$1003,SALES_TRACKER!$B$4:$B$1003,A14)),0) -> 0 | G14: =IFERROR(IF(A14="",0,E14-F14),0) -> 0 | H14: {=IFERROR(IF(A14="",0,INDEX(HPP_ENGINE!$I:$I,MATCH(A14,HPP_ENGINE!$A:$A,0))),0)} -> 0 | I14: =IFERROR(IF(A14="",0,SUMIFS(SALES_TRACKER!$G$4:$G$1003,SALES_TRACKER!$B$4:$B$1003,A14)),0) -> 0 | J14: =IFERROR(IF(A14="",0,I14-H14),0) -> 0 | K14: =IFERROR(IF(A14="",0,IF(I14=0,IF(H14>0,-1,0),J14/I14)),0) -> 0 | L14: =IFERROR(IF(OR(A14="",H14=0),0,J14/H14),0) -> 0 | M14: =IFERROR(IF(OR(A14="",E14=0),0,F14/E14),0) -> 0 | N14: =IFERROR(IF(A14="","—",IF(COUNTIF(HPP_ENGINE!$A$4:$A$203,A14)=0,"⚠ BELUM DI HPP",IF(E14=0,"PLANNING",IF(M14>=1,"SOLD OUT",IF(M14>=0.7,"ON TRACK",IF(M14>=0.3,"SLOW MOVE",IF(M14>0,"STUCK","BELUM TERJUAL"))))))),"—") -> —
B15: {=IFERROR(IF(A15="","",INDEX(HPP_ENGINE!$B:$B,MATCH(A15,HPP_ENGINE!$A:$A,0))),"")} | C15: {=IFERROR(IF(A15="","",INDEX(HPP_ENGINE!$C:$C,MATCH(A15,HPP_ENGINE!$A:$A,0))),"")} | D15: {=IFERROR(IF(A15="",0,INDEX(PRODUCTION_PLAN!$D:$D,MATCH(A15,PRODUCTION_PLAN!$A:$A,0))),0)} -> 0 | E15: {=IFERROR(IF(A15="",0,INDEX(HPP_ENGINE!$D:$D,MATCH(A15,HPP_ENGINE!$A:$A,0))),0)} -> 0 | F15: =IFERROR(IF(A15="",0,SUMIFS(SALES_TRACKER!$E$4:$E$1003,SALES_TRACKER!$B$4:$B$1003,A15)),0) -> 0 | G15: =IFERROR(IF(A15="",0,E15-F15),0) -> 0 | H15: {=IFERROR(IF(A15="",0,INDEX(HPP_ENGINE!$I:$I,MATCH(A15,HPP_ENGINE!$A:$A,0))),0)} -> 0 | I15: =IFERROR(IF(A15="",0,SUMIFS(SALES_TRACKER!$G$4:$G$1003,SALES_TRACKER!$B$4:$B$1003,A15)),0) -> 0 | J15: =IFERROR(IF(A15="",0,I15-H15),0) -> 0 | K15: =IFERROR(IF(A15="",0,IF(I15=0,IF(H15>0,-1,0),J15/I15)),0) -> 0 | L15: =IFERROR(IF(OR(A15="",H15=0),0,J15/H15),0) -> 0 | M15: =IFERROR(IF(OR(A15="",E15=0),0,F15/E15),0) -> 0 | N15: =IFERROR(IF(A15="","—",IF(COUNTIF(HPP_ENGINE!$A$4:$A$203,A15)=0,"⚠ BELUM DI HPP",IF(E15=0,"PLANNING",IF(M15>=1,"SOLD OUT",IF(M15>=0.7,"ON TRACK",IF(M15>=0.3,"SLOW MOVE",IF(M15>0,"STUCK","BELUM TERJUAL"))))))),"—") -> —
B16: {=IFERROR(IF(A16="","",INDEX(HPP_ENGINE!$B:$B,MATCH(A16,HPP_ENGINE!$A:$A,0))),"")} | C16: {=IFERROR(IF(A16="","",INDEX(HPP_ENGINE!$C:$C,MATCH(A16,HPP_ENGINE!$A:$A,0))),"")} | D16: {=IFERROR(IF(A16="",0,INDEX(PRODUCTION_PLAN!$D:$D,MATCH(A16,PRODUCTION_PLAN!$A:$A,0))),0)} -> 0 | E16: {=IFERROR(IF(A16="",0,INDEX(HPP_ENGINE!$D:$D,MATCH(A16,HPP_ENGINE!$A:$A,0))),0)} -> 0 | F16: =IFERROR(IF(A16="",0,SUMIFS(SALES_TRACKER!$E$4:$E$1003,SALES_TRACKER!$B$4:$B$1003,A16)),0) -> 0 | G16: =IFERROR(IF(A16="",0,E16-F16),0) -> 0 | H16: {=IFERROR(IF(A16="",0,INDEX(HPP_ENGINE!$I:$I,MATCH(A16,HPP_ENGINE!$A:$A,0))),0)} -> 0 | I16: =IFERROR(IF(A16="",0,SUMIFS(SALES_TRACKER!$G$4:$G$1003,SALES_TRACKER!$B$4:$B$1003,A16)),0) -> 0 | J16: =IFERROR(IF(A16="",0,I16-H16),0) -> 0 | K16: =IFERROR(IF(A16="",0,IF(I16=0,IF(H16>0,-1,0),J16/I16)),0) -> 0 | L16: =IFERROR(IF(OR(A16="",H16=0),0,J16/H16),0) -> 0 | M16: =IFERROR(IF(OR(A16="",E16=0),0,F16/E16),0) -> 0 | N16: =IFERROR(IF(A16="","—",IF(COUNTIF(HPP_ENGINE!$A$4:$A$203,A16)=0,"⚠ BELUM DI HPP",IF(E16=0,"PLANNING",IF(M16>=1,"SOLD OUT",IF(M16>=0.7,"ON TRACK",IF(M16>=0.3,"SLOW MOVE",IF(M16>0,"STUCK","BELUM TERJUAL"))))))),"—") -> —
B17: {=IFERROR(IF(A17="","",INDEX(HPP_ENGINE!$B:$B,MATCH(A17,HPP_ENGINE!$A:$A,0))),"")} | C17: {=IFERROR(IF(A17="","",INDEX(HPP_ENGINE!$C:$C,MATCH(A17,HPP_ENGINE!$A:$A,0))),"")} | D17: {=IFERROR(IF(A17="",0,INDEX(PRODUCTION_PLAN!$D:$D,MATCH(A17,PRODUCTION_PLAN!$A:$A,0))),0)} -> 0 | E17: {=IFERROR(IF(A17="",0,INDEX(HPP_ENGINE!$D:$D,MATCH(A17,HPP_ENGINE!$A:$A,0))),0)} -> 0 | F17: =IFERROR(IF(A17="",0,SUMIFS(SALES_TRACKER!$E$4:$E$1003,SALES_TRACKER!$B$4:$B$1003,A17)),0) -> 0 | G17: =IFERROR(IF(A17="",0,E17-F17),0) -> 0 | H17: {=IFERROR(IF(A17="",0,INDEX(HPP_ENGINE!$I:$I,MATCH(A17,HPP_ENGINE!$A:$A,0))),0)} -> 0 | I17: =IFERROR(IF(A17="",0,SUMIFS(SALES_TRACKER!$G$4:$G$1003,SALES_TRACKER!$B$4:$B$1003,A17)),0) -> 0 | J17: =IFERROR(IF(A17="",0,I17-H17),0) -> 0 | K17: =IFERROR(IF(A17="",0,IF(I17=0,IF(H17>0,-1,0),J17/I17)),0) -> 0 | L17: =IFERROR(IF(OR(A17="",H17=0),0,J17/H17),0) -> 0 | M17: =IFERROR(IF(OR(A17="",E17=0),0,F17/E17),0) -> 0 | N17: =IFERROR(IF(A17="","—",IF(COUNTIF(HPP_ENGINE!$A$4:$A$203,A17)=0,"⚠ BELUM DI HPP",IF(E17=0,"PLANNING",IF(M17>=1,"SOLD OUT",IF(M17>=0.7,"ON TRACK",IF(M17>=0.3,"SLOW MOVE",IF(M17>0,"STUCK","BELUM TERJUAL"))))))),"—") -> —
B18: {=IFERROR(IF(A18="","",INDEX(HPP_ENGINE!$B:$B,MATCH(A18,HPP_ENGINE!$A:$A,0))),"")} | C18: {=IFERROR(IF(A18="","",INDEX(HPP_ENGINE!$C:$C,MATCH(A18,HPP_ENGINE!$A:$A,0))),"")} | D18: {=IFERROR(IF(A18="",0,INDEX(PRODUCTION_PLAN!$D:$D,MATCH(A18,PRODUCTION_PLAN!$A:$A,0))),0)} -> 0 | E18: {=IFERROR(IF(A18="",0,INDEX(HPP_ENGINE!$D:$D,MATCH(A18,HPP_ENGINE!$A:$A,0))),0)} -> 0 | F18: =IFERROR(IF(A18="",0,SUMIFS(SALES_TRACKER!$E$4:$E$1003,SALES_TRACKER!$B$4:$B$1003,A18)),0) -> 0 | G18: =IFERROR(IF(A18="",0,E18-F18),0) -> 0 | H18: {=IFERROR(IF(A18="",0,INDEX(HPP_ENGINE!$I:$I,MATCH(A18,HPP_ENGINE!$A:$A,0))),0)} -> 0 | I18: =IFERROR(IF(A18="",0,SUMIFS(SALES_TRACKER!$G$4:$G$1003,SALES_TRACKER!$B$4:$B$1003,A18)),0) -> 0 | J18: =IFERROR(IF(A18="",0,I18-H18),0) -> 0 | K18: =IFERROR(IF(A18="",0,IF(I18=0,IF(H18>0,-1,0),J18/I18)),0) -> 0 | L18: =IFERROR(IF(OR(A18="",H18=0),0,J18/H18),0) -> 0 | M18: =IFERROR(IF(OR(A18="",E18=0),0,F18/E18),0) -> 0 | N18: =IFERROR(IF(A18="","—",IF(COUNTIF(HPP_ENGINE!$A$4:$A$203,A18)=0,"⚠ BELUM DI HPP",IF(E18=0,"PLANNING",IF(M18>=1,"SOLD OUT",IF(M18>=0.7,"ON TRACK",IF(M18>=0.3,"SLOW MOVE",IF(M18>0,"STUCK","BELUM TERJUAL"))))))),"—") -> —
B19: {=IFERROR(IF(A19="","",INDEX(HPP_ENGINE!$B:$B,MATCH(A19,HPP_ENGINE!$A:$A,0))),"")} | C19: {=IFERROR(IF(A19="","",INDEX(HPP_ENGINE!$C:$C,MATCH(A19,HPP_ENGINE!$A:$A,0))),"")} | D19: {=IFERROR(IF(A19="",0,INDEX(PRODUCTION_PLAN!$D:$D,MATCH(A19,PRODUCTION_PLAN!$A:$A,0))),0)} -> 0 | E19: {=IFERROR(IF(A19="",0,INDEX(HPP_ENGINE!$D:$D,MATCH(A19,HPP_ENGINE!$A:$A,0))),0)} -> 0 | F19: =IFERROR(IF(A19="",0,SUMIFS(SALES_TRACKER!$E$4:$E$1003,SALES_TRACKER!$B$4:$B$1003,A19)),0) -> 0 | G19: =IFERROR(IF(A19="",0,E19-F19),0) -> 0 | H19: {=IFERROR(IF(A19="",0,INDEX(HPP_ENGINE!$I:$I,MATCH(A19,HPP_ENGINE!$A:$A,0))),0)} -> 0 | I19: =IFERROR(IF(A19="",0,SUMIFS(SALES_TRACKER!$G$4:$G$1003,SALES_TRACKER!$B$4:$B$1003,A19)),0) -> 0 | J19: =IFERROR(IF(A19="",0,I19-H19),0) -> 0 | K19: =IFERROR(IF(A19="",0,IF(I19=0,IF(H19>0,-1,0),J19/I19)),0) -> 0 | L19: =IFERROR(IF(OR(A19="",H19=0),0,J19/H19),0) -> 0 | M19: =IFERROR(IF(OR(A19="",E19=0),0,F19/E19),0) -> 0 | N19: =IFERROR(IF(A19="","—",IF(COUNTIF(HPP_ENGINE!$A$4:$A$203,A19)=0,"⚠ BELUM DI HPP",IF(E19=0,"PLANNING",IF(M19>=1,"SOLD OUT",IF(M19>=0.7,"ON TRACK",IF(M19>=0.3,"SLOW MOVE",IF(M19>0,"STUCK","BELUM TERJUAL"))))))),"—") -> —
B20: {=IFERROR(IF(A20="","",INDEX(HPP_ENGINE!$B:$B,MATCH(A20,HPP_ENGINE!$A:$A,0))),"")} | C20: {=IFERROR(IF(A20="","",INDEX(HPP_ENGINE!$C:$C,MATCH(A20,HPP_ENGINE!$A:$A,0))),"")} | D20: {=IFERROR(IF(A20="",0,INDEX(PRODUCTION_PLAN!$D:$D,MATCH(A20,PRODUCTION_PLAN!$A:$A,0))),0)} -> 0 | E20: {=IFERROR(IF(A20="",0,INDEX(HPP_ENGINE!$D:$D,MATCH(A20,HPP_ENGINE!$A:$A,0))),0)} -> 0 | F20: =IFERROR(IF(A20="",0,SUMIFS(SALES_TRACKER!$E$4:$E$1003,SALES_TRACKER!$B$4:$B$1003,A20)),0) -> 0 | G20: =IFERROR(IF(A20="",0,E20-F20),0) -> 0 | H20: {=IFERROR(IF(A20="",0,INDEX(HPP_ENGINE!$I:$I,MATCH(A20,HPP_ENGINE!$A:$A,0))),0)} -> 0 | I20: =IFERROR(IF(A20="",0,SUMIFS(SALES_TRACKER!$G$4:$G$1003,SALES_TRACKER!$B$4:$B$1003,A20)),0) -> 0 | J20: =IFERROR(IF(A20="",0,I20-H20),0) -> 0 | K20: =IFERROR(IF(A20="",0,IF(I20=0,IF(H20>0,-1,0),J20/I20)),0) -> 0 | L20: =IFERROR(IF(OR(A20="",H20=0),0,J20/H20),0) -> 0 | M20: =IFERROR(IF(OR(A20="",E20=0),0,F20/E20),0) -> 0 | N20: =IFERROR(IF(A20="","—",IF(COUNTIF(HPP_ENGINE!$A$4:$A$203,A20)=0,"⚠ BELUM DI HPP",IF(E20=0,"PLANNING",IF(M20>=1,"SOLD OUT",IF(M20>=0.7,"ON TRACK",IF(M20>=0.3,"SLOW MOVE",IF(M20>0,"STUCK","BELUM TERJUAL"))))))),"—") -> —
B21: {=IFERROR(IF(A21="","",INDEX(HPP_ENGINE!$B:$B,MATCH(A21,HPP_ENGINE!$A:$A,0))),"")} | C21: {=IFERROR(IF(A21="","",INDEX(HPP_ENGINE!$C:$C,MATCH(A21,HPP_ENGINE!$A:$A,0))),"")} | D21: {=IFERROR(IF(A21="",0,INDEX(PRODUCTION_PLAN!$D:$D,MATCH(A21,PRODUCTION_PLAN!$A:$A,0))),0)} -> 0 | E21: {=IFERROR(IF(A21="",0,INDEX(HPP_ENGINE!$D:$D,MATCH(A21,HPP_ENGINE!$A:$A,0))),0)} -> 0 | F21: =IFERROR(IF(A21="",0,SUMIFS(SALES_TRACKER!$E$4:$E$1003,SALES_TRACKER!$B$4:$B$1003,A21)),0) -> 0 | G21: =IFERROR(IF(A21="",0,E21-F21),0) -> 0 | H21: {=IFERROR(IF(A21="",0,INDEX(HPP_ENGINE!$I:$I,MATCH(A21,HPP_ENGINE!$A:$A,0))),0)} -> 0 | I21: =IFERROR(IF(A21="",0,SUMIFS(SALES_TRACKER!$G$4:$G$1003,SALES_TRACKER!$B$4:$B$1003,A21)),0) -> 0 | J21: =IFERROR(IF(A21="",0,I21-H21),0) -> 0 | K21: =IFERROR(IF(A21="",0,IF(I21=0,IF(H21>0,-1,0),J21/I21)),0) -> 0 | L21: =IFERROR(IF(OR(A21="",H21=0),0,J21/H21),0) -> 0 | M21: =IFERROR(IF(OR(A21="",E21=0),0,F21/E21),0) -> 0 | N21: =IFERROR(IF(A21="","—",IF(COUNTIF(HPP_ENGINE!$A$4:$A$203,A21)=0,"⚠ BELUM DI HPP",IF(E21=0,"PLANNING",IF(M21>=1,"SOLD OUT",IF(M21>=0.7,"ON TRACK",IF(M21>=0.3,"SLOW MOVE",IF(M21>0,"STUCK","BELUM TERJUAL"))))))),"—") -> —
B22: {=IFERROR(IF(A22="","",INDEX(HPP_ENGINE!$B:$B,MATCH(A22,HPP_ENGINE!$A:$A,0))),"")} | C22: {=IFERROR(IF(A22="","",INDEX(HPP_ENGINE!$C:$C,MATCH(A22,HPP_ENGINE!$A:$A,0))),"")} | D22: {=IFERROR(IF(A22="",0,INDEX(PRODUCTION_PLAN!$D:$D,MATCH(A22,PRODUCTION_PLAN!$A:$A,0))),0)} -> 0 | E22: {=IFERROR(IF(A22="",0,INDEX(HPP_ENGINE!$D:$D,MATCH(A22,HPP_ENGINE!$A:$A,0))),0)} -> 0 | F22: =IFERROR(IF(A22="",0,SUMIFS(SALES_TRACKER!$E$4:$E$1003,SALES_TRACKER!$B$4:$B$1003,A22)),0) -> 0 | G22: =IFERROR(IF(A22="",0,E22-F22),0) -> 0 | H22: {=IFERROR(IF(A22="",0,INDEX(HPP_ENGINE!$I:$I,MATCH(A22,HPP_ENGINE!$A:$A,0))),0)} -> 0 | I22: =IFERROR(IF(A22="",0,SUMIFS(SALES_TRACKER!$G$4:$G$1003,SALES_TRACKER!$B$4:$B$1003,A22)),0) -> 0 | J22: =IFERROR(IF(A22="",0,I22-H22),0) -> 0 | K22: =IFERROR(IF(A22="",0,IF(I22=0,IF(H22>0,-1,0),J22/I22)),0) -> 0 | L22: =IFERROR(IF(OR(A22="",H22=0),0,J22/H22),0) -> 0 | M22: =IFERROR(IF(OR(A22="",E22=0),0,F22/E22),0) -> 0 | N22: =IFERROR(IF(A22="","—",IF(COUNTIF(HPP_ENGINE!$A$4:$A$203,A22)=0,"⚠ BELUM DI HPP",IF(E22=0,"PLANNING",IF(M22>=1,"SOLD OUT",IF(M22>=0.7,"ON TRACK",IF(M22>=0.3,"SLOW MOVE",IF(M22>0,"STUCK","BELUM TERJUAL"))))))),"—") -> —
... B203: {=IFERROR(IF(A203="","",INDEX(HPP_ENGINE!$B:$B,MATCH(A203,HPP_ENGINE!$A:$A,0))),"")} | C203: {=IFERROR(IF(A203="","",INDEX(HPP_ENGINE!$C:$C,MATCH(A203,HPP_ENGINE!$A:$A,0))),"")} | D203: {=IFERROR(IF(A203="",0,INDEX(PRODUCTION_PLAN!$D:$D,MATCH(A203,PRODUCTION_PLAN!$A:$A,0))),0)} -> 0 | E203: {=IFERROR(IF(A203="",0,INDEX(HPP_ENGINE!$D:$D,MATCH(A203,HPP_ENGINE!$A:$A,0))),0)} -> 0 | F203: =IFERROR(IF(A203="",0,SUMIFS(SALES_TRACKER!$E$4:$E$1003,SALES_TRACKER!$B$4:$B$1003,A203)),0) -> 0 | G203: =IFERROR(IF(A203="",0,E203-F203),0) -> 0 | H203: {=IFERROR(IF(A203="",0,INDEX(HPP_ENGINE!$I:$I,MATCH(A203,HPP_ENGINE!$A:$A,0))),0)} -> 0 | I203: =IFERROR(IF(A203="",0,SUMIFS(SALES_TRACKER!$G$4:$G$1003,SALES_TRACKER!$B$4:$B$1003,A203)),0) -> 0 | J203: =IFERROR(IF(A203="",0,I203-H203),0) -> 0 | K203: =IFERROR(IF(A203="",0,IF(I203=0,IF(H203>0,-1,0),J203/I203)),0) -> 0 | L203: =IFERROR(IF(OR(A203="",H203=0),0,J203/H203),0) -> 0 | M203: =IFERROR(IF(OR(A203="",E203=0),0,F203/E203),0) -> 0 | N203: =IFERROR(IF(A203="","—",IF(COUNTIF(HPP_ENGINE!$A$4:$A$203,A203)=0,"⚠ BELUM DI HPP",IF(E203=0,"PLANNING",IF(M203>=1,"SOLD OUT",IF(M203>=0.7,"ON TRACK",IF(M203>=0.3,"SLOW MOVE",IF(M203>0,"STUCK","BELUM TERJUAL"))))))),"—") -> —

Sheet CASHFLOW
A1: ◆ CASHFLOW · Arus Kas Masuk & Keluar · Saldo Real-Time ◆
A2: BIRU = isi manual (Tanggal, ORDER_ID, Tipe, Nominal, Keterangan, Kategori) · EMAS = otomatis · Kapasitas: 1.000 transaksi
A3: TANGGAL | B3: ORDER_ID | C3: TIPE | D3: NOMINAL (Rp) | E3: KETERANGAN | F3: KATEGORI | G3: SALDO KUMULATIF (Rp) | H3: STATUS KAS | I3: PERIODE
A4: 2026-03-27 | B4: HZN-2604-001 | C4: Masuk | D4: 26250000 | E4: DP 50% Elara Boutique | F4: Revenue | G4: =IFERROR(IF(A4="",0,IF(C4="Masuk",D4,IF(C4="Keluar",-D4,0))),0) -> 26250000 | H4: =IFERROR(IF(A4="","—",IF(G4<0,"🚨 NEGATIF",IF(G4<50000000,"⚡ KRITIS",IF(G4<150000000,"✓ AMAN","💎 EXCELLENT")))),"—") -> ⚡ KRITIS | I4: =IFERROR(IF(A4="","",TEXT(A4,"MMM YYYY")),"—") -> Mar 2026
A5: 2026-03-27 | B5: HZN-2604-001 | C5: Keluar | D5: 22000000 | E5: Beli bahan Abaya 150pcs | F5: Bahan | G5: =IFERROR(IF(A5="",0,G4+IF(C5="Masuk",D5,IF(C5="Keluar",-D5,0))),0) -> 4250000 | H5: =IFERROR(IF(A5="","—",IF(G5<0,"🚨 NEGATIF",IF(G5<50000000,"⚡ KRITIS",IF(G5<150000000,"✓ AMAN","💎 EXCELLENT")))),"—") -> ⚡ KRITIS | I5: =IFERROR(IF(A5="","",TEXT(A5,"MMM YYYY")),"—") -> Mar 2026
A6: 2026-03-31 | B6: HZN-2604-002 | C6: Masuk | D6: 45000000 | E6: DP 50% Atelier Nusantara | F6: Revenue | G6: =IFERROR(IF(A6="",0,G5+IF(C6="Masuk",D6,IF(C6="Keluar",-D6,0))),0) -> 49250000 | H6: =IFERROR(IF(A6="","—",IF(G6<0,"🚨 NEGATIF",IF(G6<50000000,"⚡ KRITIS",IF(G6<150000000,"✓ AMAN","💎 EXCELLENT")))),"—") -> ⚡ KRITIS | I6: =IFERROR(IF(A6="","",TEXT(A6,"MMM YYYY")),"—") -> Mar 2026
A7: 2026-03-31 | B7: HZN-2604-002 | C7: Keluar | D7: 35000000 | E7: Beli bahan Gamis 200pcs | F7: Bahan | G7: =IFERROR(IF(A7="",0,G6+IF(C7="Masuk",D7,IF(C7="Keluar",-D7,0))),0) -> 14250000 | H7: =IFERROR(IF(A7="","—",IF(G7<0,"🚨 NEGATIF",IF(G7<50000000,"⚡ KRITIS",IF(G7<150000000,"✓ AMAN","💎 EXCELLENT")))),"—") -> ⚡ KRITIS | I7: =IFERROR(IF(A7="","",TEXT(A7,"MMM YYYY")),"—") -> Mar 2026
A8: 2026-04-02 | B8: HZN-2604-006 | C8: Masuk | D8: 43750000 | E8: DP 50% CV Mitra Busana | F8: Revenue | G8: =IFERROR(IF(A8="",0,G7+IF(C8="Masuk",D8,IF(C8="Keluar",-D8,0))),0) -> 58000000 | H8: =IFERROR(IF(A8="","—",IF(G8<0,"🚨 NEGATIF",IF(G8<50000000,"⚡ KRITIS",IF(G8<150000000,"✓ AMAN","💎 EXCELLENT")))),"—") -> ✓ AMAN | I8: =IFERROR(IF(A8="","",TEXT(A8,"MMM YYYY")),"—") -> Apr 2026
A9: 2026-04-02 | B9: HZN-2604-006 | C9: Keluar | D9: 36750000 | E9: Beli bahan Abaya 250pcs | F9: Bahan | G9: =IFERROR(IF(A9="",0,G8+IF(C9="Masuk",D9,IF(C9="Keluar",-D9,0))),0) -> 21250000 | H9: =IFERROR(IF(A9="","—",IF(G9<0,"🚨 NEGATIF",IF(G9<50000000,"⚡ KRITIS",IF(G9<150000000,"✓ AMAN","💎 EXCELLENT")))),"—") -> ⚡ KRITIS | I9: =IFERROR(IF(A9="","",TEXT(A9,"MMM YYYY")),"—") -> Apr 2026
A10: 2026-04-05 | B10: HZN-2604-007 | C10: Masuk | D10: 40500000 | E10: DP 50% Rumah Mode Sari | F10: Revenue | G10: =IFERROR(IF(A10="",0,G9+IF(C10="Masuk",D10,IF(C10="Keluar",-D10,0))),0) -> 61750000 | H10: =IFERROR(IF(A10="","—",IF(G10<0,"🚨 NEGATIF",IF(G10<50000000,"⚡ KRITIS",IF(G10<150000000,"✓ AMAN","💎 EXCELLENT")))),"—") -> ✓ AMAN | I10: =IFERROR(IF(A10="","",TEXT(A10,"MMM YYYY")),"—") -> Apr 2026
A11: 2026-04-05 | B11: HZN-2604-007 | C11: Keluar | D11: 31450000 | E11: Beli bahan Gamis 180pcs | F11: Bahan | G11: =IFERROR(IF(A11="",0,G10+IF(C11="Masuk",D11,IF(C11="Keluar",-D11,0))),0) -> 30300000 | H11: =IFERROR(IF(A11="","—",IF(G11<0,"🚨 NEGATIF",IF(G11<50000000,"⚡ KRITIS",IF(G11<150000000,"✓ AMAN","💎 EXCELLENT")))),"—") -> ⚡ KRITIS | I11: =IFERROR(IF(A11="","",TEXT(A11,"MMM YYYY")),"—") -> Apr 2026
A12: 2026-04-07 | B12: HZN-2604-003 | C12: Masuk | D12: 13920000 | E12: DP 30% House of Laras | F12: Revenue | G12: =IFERROR(IF(A12="",0,G11+IF(C12="Masuk",D12,IF(C12="Keluar",-D12,0))),0) -> 44220000 | H12: =IFERROR(IF(A12="","—",IF(G12<0,"🚨 NEGATIF",IF(G12<50000000,"⚡ KRITIS",IF(G12<150000000,"✓ AMAN","💎 EXCELLENT")))),"—") -> ⚡ KRITIS | I12: =IFERROR(IF(A12="","",TEXT(A12,"MMM YYYY")),"—") -> Apr 2026
A13: 2026-04-07 | B13: HZN-2604-004 | C13: Masuk | D13: 13500000 | E13: Pelunasan 50% Butik Seruni | F13: Revenue | G13: =IFERROR(IF(A13="",0,G12+IF(C13="Masuk",D13,IF(C13="Keluar",-D13,0))),0) -> 57720000 | H13: =IFERROR(IF(A13="","—",IF(G13<0,"🚨 NEGATIF",IF(G13<50000000,"⚡ KRITIS",IF(G13<150000000,"✓ AMAN","💎 EXCELLENT")))),"—") -> ✓ AMAN | I13: =IFERROR(IF(A13="","",TEXT(A13,"MMM YYYY")),"—") -> Apr 2026
A14: 2026-04-08 | B14: HZN-2604-001 | C14: Masuk | D14: 52080000 | E14: Pembayaran penjualan Elara | F14: Revenue | G14: =IFERROR(IF(A14="",0,G13+IF(C14="Masuk",D14,IF(C14="Keluar",-D14,0))),0) -> 109800000 | H14: =IFERROR(IF(A14="","—",IF(G14<0,"🚨 NEGATIF",IF(G14<50000000,"⚡ KRITIS",IF(G14<150000000,"✓ AMAN","💎 EXCELLENT")))),"—") -> ✓ AMAN | I14: =IFERROR(IF(A14="","",TEXT(A14,"MMM YYYY")),"—") -> Apr 2026
A15: 2026-04-08 | B15: HZN-2604-004 | C15: Masuk | D15: 13500000 | E15: Pembayaran final Butik Seruni | F15: Revenue | G15: =IFERROR(IF(A15="",0,G14+IF(C15="Masuk",D15,IF(C15="Keluar",-D15,0))),0) -> 123300000 | H15: =IFERROR(IF(A15="","—",IF(G15<0,"🚨 NEGATIF",IF(G15<50000000,"⚡ KRITIS",IF(G15<150000000,"✓ AMAN","💎 EXCELLENT")))),"—") -> ✓ AMAN | I15: =IFERROR(IF(A15="","",TEXT(A15,"MMM YYYY")),"—") -> Apr 2026
A16: 2026-04-09 | B16: — | C16: Keluar | D16: 8500000 | E16: Upah TK minggu ini | F16: TK | G16: =IFERROR(IF(A16="",0,G15+IF(C16="Masuk",D16,IF(C16="Keluar",-D16,0))),0) -> 114800000 | H16: =IFERROR(IF(A16="","—",IF(G16<0,"🚨 NEGATIF",IF(G16<50000000,"⚡ KRITIS",IF(G16<150000000,"✓ AMAN","💎 EXCELLENT")))),"—") -> ✓ AMAN | I16: =IFERROR(IF(A16="","",TEXT(A16,"MMM YYYY")),"—") -> Apr 2026
A17: 2026-04-10 | B17: — | C17: Keluar | D17: 3500000 | E17: Overhead operasional April | F17: Overhead | G17: =IFERROR(IF(A17="",0,G16+IF(C17="Masuk",D17,IF(C17="Keluar",-D17,0))),0) -> 111300000 | H17: =IFERROR(IF(A17="","—",IF(G17<0,"🚨 NEGATIF",IF(G17<50000000,"⚡ KRITIS",IF(G17<150000000,"✓ AMAN","💎 EXCELLENT")))),"—") -> ✓ AMAN | I17: =IFERROR(IF(A17="","",TEXT(A17,"MMM YYYY")),"—") -> Apr 2026
G18: =IFERROR(IF(A18="",0,G17+IF(C18="Masuk",D18,IF(C18="Keluar",-D18,0))),0) -> 0 | H18: =IFERROR(IF(A18="","—",IF(G18<0,"🚨 NEGATIF",IF(G18<50000000,"⚡ KRITIS",IF(G18<150000000,"✓ AMAN","💎 EXCELLENT")))),"—") -> — | I18: =IFERROR(IF(A18="","",TEXT(A18,"MMM YYYY")),"—")
G19: =IFERROR(IF(A19="",0,G18+IF(C19="Masuk",D19,IF(C19="Keluar",-D19,0))),0) -> 0 | H19: =IFERROR(IF(A19="","—",IF(G19<0,"🚨 NEGATIF",IF(G19<50000000,"⚡ KRITIS",IF(G19<150000000,"✓ AMAN","💎 EXCELLENT")))),"—") -> — | I19: =IFERROR(IF(A19="","",TEXT(A19,"MMM YYYY")),"—")
G20: =IFERROR(IF(A20="",0,G19+IF(C20="Masuk",D20,IF(C20="Keluar",-D20,0))),0) -> 0 | H20: =IFERROR(IF(A20="","—",IF(G20<0,"🚨 NEGATIF",IF(G20<50000000,"⚡ KRITIS",IF(G20<150000000,"✓ AMAN","💎 EXCELLENT")))),"—") -> — | I20: =IFERROR(IF(A20="","",TEXT(A20,"MMM YYYY")),"—")
G21: =IFERROR(IF(A21="",0,G20+IF(C21="Masuk",D21,IF(C21="Keluar",-D21,0))),0) -> 0 | H21: =IFERROR(IF(A21="","—",IF(G21<0,"🚨 NEGATIF",IF(G21<50000000,"⚡ KRITIS",IF(G21<150000000,"✓ AMAN","💎 EXCELLENT")))),"—") -> — | I21: =IFERROR(IF(A21="","",TEXT(A21,"MMM YYYY")),"—")
G22: =IFERROR(IF(A22="",0,G21+IF(C22="Masuk",D22,IF(C22="Keluar",-D22,0))),0) -> 0 | H22: =IFERROR(IF(A22="","—",IF(G22<0,"🚨 NEGATIF",IF(G22<50000000,"⚡ KRITIS",IF(G22<150000000,"✓ AMAN","💎 EXCELLENT")))),"—") -> — | I22: =IFERROR(IF(A22="","",TEXT(A22,"MMM YYYY")),"—")
G23: =IFERROR(IF(A23="",0,G22+IF(C23="Masuk",D23,IF(C23="Keluar",-D23,0))),0) -> 0 | H23: =IFERROR(IF(A23="","—",IF(G23<0,"🚨 NEGATIF",IF(G23<50000000,"⚡ KRITIS",IF(G23<150000000,"✓ AMAN","💎 EXCELLENT")))),"—") -> — | I23: =IFERROR(IF(A23="","",TEXT(A23,"MMM YYYY")),"—")
G24: =IFERROR(IF(A24="",0,G23+IF(C24="Masuk",D24,IF(C24="Keluar",-D24,0))),0) -> 0 | H24: =IFERROR(IF(A24="","—",IF(G24<0,"🚨 NEGATIF",IF(G24<50000000,"⚡ KRITIS",IF(G24<150000000,"✓ AMAN","💎 EXCELLENT")))),"—") -> — | I24: =IFERROR(IF(A24="","",TEXT(A24,"MMM YYYY")),"—")
G25: =IFERROR(IF(A25="",0,G24+IF(C25="Masuk",D25,IF(C25="Keluar",-D25,0))),0) -> 0 | H25: =IFERROR(IF(A25="","—",IF(G25<0,"🚨 NEGATIF",IF(G25<50000000,"⚡ KRITIS",IF(G25<150000000,"✓ AMAN","💎 EXCELLENT")))),"—") -> — | I25: =IFERROR(IF(A25="","",TEXT(A25,"MMM YYYY")),"—")
G26: =IFERROR(IF(A26="",0,G25+IF(C26="Masuk",D26,IF(C26="Keluar",-D26,0))),0) -> 0 | H26: =IFERROR(IF(A26="","—",IF(G26<0,"🚨 NEGATIF",IF(G26<50000000,"⚡ KRITIS",IF(G26<150000000,"✓ AMAN","💎 EXCELLENT")))),"—") -> — | I26: =IFERROR(IF(A26="","",TEXT(A26,"MMM YYYY")),"—")
G27: =IFERROR(IF(A27="",0,G26+IF(C27="Masuk",D27,IF(C27="Keluar",-D27,0))),0) -> 0 | H27: =IFERROR(IF(A27="","—",IF(G27<0,"🚨 NEGATIF",IF(G27<50000000,"⚡ KRITIS",IF(G27<150000000,"✓ AMAN","💎 EXCELLENT")))),"—") -> — | I27: =IFERROR(IF(A27="","",TEXT(A27,"MMM YYYY")),"—")
G28: =IFERROR(IF(A28="",0,G27+IF(C28="Masuk",D28,IF(C28="Keluar",-D28,0))),0) -> 0 | H28: =IFERROR(IF(A28="","—",IF(G28<0,"🚨 NEGATIF",IF(G28<50000000,"⚡ KRITIS",IF(G28<150000000,"✓ AMAN","💎 EXCELLENT")))),"—") -> — | I28: =IFERROR(IF(A28="","",TEXT(A28,"MMM YYYY")),"—")
G29: =IFERROR(IF(A29="",0,G28+IF(C29="Masuk",D29,IF(C29="Keluar",-D29,0))),0) -> 0 | H29: =IFERROR(IF(A29="","—",IF(G29<0,"🚨 NEGATIF",IF(G29<50000000,"⚡ KRITIS",IF(G29<150000000,"✓ AMAN","💎 EXCELLENT")))),"—") -> — | I29: =IFERROR(IF(A29="","",TEXT(A29,"MMM YYYY")),"—")
... G1003: =IFERROR(IF(A1003="",0,G1002+IF(C1003="Masuk",D1003,IF(C1003="Keluar",-D1003,0))),0) -> 0 | H1003: =IFERROR(IF(A1003="","—",IF(G1003<0,"🚨 NEGATIF",IF(G1003<50000000,"⚡ KRITIS",IF(G1003<150000000,"✓ AMAN","💎 EXCELLENT")))),"—") -> — | I1003: =IFERROR(IF(A1003="","",TEXT(A1003,"MMM YYYY")),"—")

Sheet AI_ANALYSIS
A1: ◆ AI ANALYSIS · Insight Bisnis & KPI Real-Time ◆
A2: Semua otomatis — Tidak ada input manual di sheet ini · Update setiap file dibuka
A4: ◈ KPI BISNIS UTAMA — Snapshot Real-Time
A5: METRIK | B5: NILAI AKTUAL | C5: TARGET | D5: STATUS | E5: INSIGHT ANALISIS | F5: REKOMENDASI AKSI
A6: Total Revenue | B6: =IFERROR(SUMIFS(SUMMARY_ENGINE!$I:$I,SUMMARY_ENGINE!$A:$A,"HZN-*"),0) -> 113800000 | C6: ≥ Rp 300 juta | D6: =IF(B6>=300000000,"✓ TERCAPAI","⚠ KURANG") -> ⚠ KURANG | E6: Revenue aktual dari semua order yang sudah terealisasi penjualannya | F6: Dorong sell-through order STUCK · Gamis Velvet & Kaftan Silk prioritas
A7: Total Gross Profit | B7: =IFERROR(SUMIFS(SUMMARY_ENGINE!$J:$J,SUMMARY_ENGINE!$A:$A,"HZN-*"),0) -> -102167000 | C7: ≥ Rp 0 (Break Even) | D7: =IF(B7>=0,"✓ POSITIF","⚠ NEGATIF") -> ⚠ NEGATIF | E7: Net profit setelah dikurangi HPP seluruh order · Negatif jika stok belum terjual | F7: Order belum terjual menekan profit · Prioritaskan penjualan STUCK orders
A8: Margin % Aktual | B8: =IFERROR(IF(B6=0,0,B7/B6),0) -> -0.8977768 | C8: ≥ 40% (PARAM_MARGIN_TARGET) | D8: =IF(B8>=PARAM_MARGIN_TARGET,"✓ SEHAT",IF(B8>=PARAM_MARGIN_WARNING,"⚠ REVIEW","🚨 KRITIS")) -> 🚨 KRITIS | E8: Margin keseluruhan portfolio · Termasuk order belum terjual yang menekan margin | F8: Evaluasi HPP order MAHAL · Cek STATUS HPP di HPP_ENGINE
A9: Order SOLD OUT | B9: =IFERROR(COUNTIF(SUMMARY_ENGINE!$N$4:$N$203,"SOLD OUT"),0) -> 2 | C9: ≥ 3 order | D9: =IF(B9>=3,"✓ BAGUS",IF(B9>=1,"⚠ PERLU LEBIH","⚠ NIHIL")) -> ⚠ PERLU LEBIH | E9: Jumlah order yang seluruh stoknya habis terjual — indikator sell-through terbaik | F9: Replikasi strategi penjualan order Sold Out ke produk lain · Analisis klien
A10: Order STUCK/SLOW | B10: =IFERROR(COUNTIF(SUMMARY_ENGINE!$N$4:$N$203,"BELUM TERJUAL")+COUNTIF(SUMMARY_ENGINE!$N$4:$N$203,"SLOW MOVE")+COUNTIF(SUMMARY_ENGINE!$N$4:$N$203,"STUCK"),0) -> 5 | C10: = 0 order | D10: =IF(B10=0,"✓ NIHIL",IF(B10<=2,"⚠ PERHATIAN","🚨 "&B10&" ORDER")) -> 🚨 5 ORDER | E10: Order stok belum bergerak atau lambat terjual · Risiko modal tertahan | F10: Evaluasi harga & channel marketing order STUCK · Pertimbangkan konsinyasi
A11: Saldo Kas Aktual | B11: {=IFERROR(INDEX(CASHFLOW!$G:$G,MATCH(2,1/(CASHFLOW!$A:$A<>""),1)),0)} -> 111300000 | C11: ≥ Rp 50 juta | D11: =IF(B11>=50000000,"✓ AMAN",IF(B11>=0,"⚡ KRITIS","🚨 NEGATIF")) -> ✓ AMAN | E11: Posisi kas aktual setelah semua transaksi · Pakai CASHFLOW terbaru | F11: Pertahankan kas > Rp 50jt sebagai buffer operasional minimum
A12: Rata-rata Reject Rate | B12: =IFERROR(AVERAGEIFS(PRODUCTION_PLAN!$J$4:$J$203,PRODUCTION_PLAN!$A$4:$A$203,"HZN-*",PRODUCTION_PLAN!$E$4:$E$203,">"&0),0) -> 0.039106859 | C12: < 5% (PARAM_REJECT_MAX) | D12: =IF(B12<PARAM_REJECT_MAX,"✓ OK",IF(B12<0.1,"⚠ PERHATIAN","🚨 ESKALASI")) -> ✓ OK | E12: Rata-rata reject rate semua batch produksi aktif · Monitor per batch | F12: Monitor batch reject > 4% sebelum eskalasi · Review material & proses jahit
A13: Sell Through Rate | B13: =IFERROR(IF(SUMIFS(SUMMARY_ENGINE!$E:$E,SUMMARY_ENGINE!$A:$A,"HZN-*")=0,0,SUMIFS(SUMMARY_ENGINE!$F:$F,SUMMARY_ENGINE!$A:$A,"HZN-*")/SUMIFS(SUMMARY_ENGINE!$E:$E,SUMMARY_ENGINE!$A:$A,"HZN-*")),0) -> 0.37059416 | C13: ≥ 70% | D13: =IF(B13>=0.7,"✓ SEHAT",IF(B13>=0.5,"⚠ REVIEW","🚨 RENDAH")) -> 🚨 RENDAH | E13: % total unit yang sudah terjual dari total produksi seluruh order aktif | F13: Tingkatkan aktivitas penjualan B2B dan konsinyasi · Review strategi per produk
A16: ◈ DISTRIBUSI NET PROFIT — Berdasarkan PARAMETER Sistem
A17: PENERIMA | B17: PERSENTASE | C17: NOMINAL PROFIT (Rp) | D17: STATUS | E17: KETERANGAN | F17: CATATAN DISTRIBUSI
A18: Jeehana | B18: =PARAM_PCT_JEEHANA -> 0.4 | C18: =IFERROR(PARAM_PCT_JEEHANA*B7,0) -> -40866800 | D18: =IF(C18>0,"✓ "&TEXT(C18,"#,##0"),"⚠ "&TEXT(C18,"#,##0")) -> ⚠ -40.866.800 | E18: "Pemilik / Mitra 1" | F18: "% diatur di PARAMETER sheet baris PARAM_PCT_JEEHANA"
A19: Hasan | B19: =PARAM_PCT_HASAN -> 0.3 | C19: =IFERROR(PARAM_PCT_HASAN*B7,0) -> -30650100 | D19: =IF(C19>0,"✓ "&TEXT(C19,"#,##0"),"⚠ "&TEXT(C19,"#,##0")) -> ⚠ -30.650.100 | E19: "Pemilik / Mitra 2" | F19: "% diatur di PARAMETER sheet baris PARAM_PCT_HASAN"
A20: Kas Usaha | B20: =PARAM_PCT_KAS -> 0.3 | C20: =IFERROR(PARAM_PCT_KAS*B7,0) -> -30650100 | D20: =IF(C20>0,"✓ "&TEXT(C20,"#,##0"),"⚠ "&TEXT(C20,"#,##0")) -> ⚠ -30.650.100 | E20: "Dana Reinvestasi" | F20: "% diatur di PARAMETER sheet baris PARAM_PCT_KAS"
A21: TOTAL | C21: =IFERROR(C18+C19+C20,0) -> -102167000 | D21: =IF(ABS(B18+B19+B20-1)<0.001,"✓ DISTRIBUSI 100% — VALID","⚠ ERROR: Total "&TEXT(B18+B19+B20,"0%")&" — Harus 100%!") -> ✓ DISTRIBUSI 100% — VALID
